Workbook
Name CAC_Per_Logo: Assumptions!$H$20
Name Capex_Pct: Assumptions!$H$14
Name Churn_Rate: Assumptions!$H$5
Name Contraction_Rate: Assumptions!$H$7
Name Discount_Rate: Assumptions!$H$21
Name DPO: Assumptions!$H$16
Name DSO: Assumptions!$H$15
Name Expansion_Rate: Assumptions!$H$6
Name Gross_Margin: Assumptions!$H$11
Name Hiring_Pace: Assumptions!$H$10
Name Interest_Rate: Assumptions!$H$13
Name Ledger_Months: 'Customer ARR Ledger'!$A$4:A10226
Name Ledger_Movement: 'Customer ARR Ledger'!$J$4:J10226
Name Ledger_MRR: 'Customer ARR Ledger'!$F$4:F10226
Name Ledger_Status: 'Customer ARR Ledger'!$G$4:G10226
Name Merit_Increase: Assumptions!$H$12
Name Opening_Cash: Assumptions!$H$17
Name Opening_Debt: Assumptions!$H$18
Name Pipeline_Factor: Assumptions!$H$8
Name Sales_Cycle_Factor: Assumptions!$H$9
Name Scenario_Name: Assumptions!$H$25
Name Scenario_Select: Assumptions!$H$4
Name Tax_Rate: Assumptions!$H$19
Name Variance_Dollar: Assumptions!$H$23
Name Variance_Pct: Assumptions!$H$22

Sheet Cover & Instructions
A1: Northstar SaaS | Revenue Forecasting, Budget Variance & Board Reporting
B3: Q3 2026 Board Model
B5: Purpose
B6: Answer: Are we hitting revenue targets, why did we miss/beat budget, and what is the realistic FY forecast?
B8: How to use
B9: 1. Change yellow inputs on Assumptions.
B10: 2. Select Base / Upside / Downside using the Scenario Selector.
B11: 3. Review linked forecast, 3 statements, metrics, variance and sensitivities.
B12: 4. Blue font = formulas; yellow fill = editable assumption.
B15: Circularity policy
B16: Interest uses prior-period cash. Cash Flow calculates ending cash; Balance Sheet links to that result. No iterative calculation is required.
B19: Model integrity checks
B20: Balance Sheet check | C20: ='Balance Sheet'!N22 -> 0
B21: ARR bridge check | C21: ='ARR Bridge'!N11 -> 0
B22: Cash flow check | C22: ='Cash Flow Statement'!N17-'Balance Sheet'!N5 -> 0
B24: Selected scenario | C24: =INDEX(Assumptions!K3:K5,MATCH(Scenario_Select,Assumptions!J3:J5,0)) -> Base

Sheet Assumptions
A1: Assumptions | centralized, scenario-specific model drivers
B3: Driver | C3: Base | D3: Upside | E3: Downside | F3: Units | G3: Rationale | H3: Selected | J3: 1 | K3: Base
B4: Scenario Selector | C4: 1 | D4: 2 | E4: 3 | F4: 1=Base | G4: Board planning case | H4: =C4 -> 1 | J4: 2 | K4: Upside
B5: Monthly logo churn | C5: 0.011 | D5: 0.008 | E5: 0.016 | F5: % | G5: Segment-weighted logo loss | H5: =CHOOSE($H$4,C5,D5,E5) -> 0.011 | J5: 3 | K5: Downside
B6: Monthly expansion rate | C6: 0.0065 | D6: 0.0085 | E6: 0.004 | F6: % | G6: Expansion ARR on beginning ARR | H6: =CHOOSE($H$4,C6,D6,E6) -> 0.0065
B7: Monthly contraction rate | C7: 0.002 | D7: 0.0014 | E7: 0.0032 | F7: % | G7: Downgrades on beginning ARR | H7: =CHOOSE($H$4,C7,D7,E7) -> 0.002
B8: Pipeline conversion factor | C8: 0.55 | D8: 0.7 | E8: 0.38 | F8: x | G8: Applied to probability-weighted pipeline after stage weighting | H8: =CHOOSE($H$4,C8,D8,E8) -> 0.55
B9: Sales cycle timing factor | C9: 1 | D9: 0.92 | E9: 1.18 | F9: x | G9: Changes timing / close slippage | H9: =CHOOSE($H$4,C9,D9,E9) -> 1
B10: Hiring pace | C10: 1 | D10: 1.08 | E10: 0.82 | F10: x | G10: Scales planned headcount spend | H10: =CHOOSE($H$4,C10,D10,E10) -> 1
B11: Gross margin | C11: 0.805 | D11: 0.815 | E11: 0.785 | F11: % | G11: Subscription delivery margin | H11: =CHOOSE($H$4,C11,D11,E11) -> 0.805
B12: Annual merit increase | C12: 0.04 | D12: 0.04 | E12: 0.03 | F12: % | G12: Compensation inflation | H12: =CHOOSE($H$4,C12,D12,E12) -> 0.04
B13: Interest rate on cash | C13: 0.045 | D13: 0.048 | E13: 0.04 | F13: % | G13: Beginning-cash circularity breaker | H13: =CHOOSE($H$4,C13,D13,E13) -> 0.045
B14: Capex as % revenue | C14: 0.025 | D14: 0.024 | E14: 0.02 | F14: % | G14: Capitalized internal systems | H14: =CHOOSE($H$4,C14,D14,E14) -> 0.025
B15: DSO | C15: 48 | D15: 44 | E15: 55 | F15: days | G15: Collections efficiency | H15: =CHOOSE($H$4,C15,D15,E15) -> 48
B16: DPO | C16: 32 | D16: 36 | E16: 28 | F16: days | G16: Vendor payment timing | H16: =CHOOSE($H$4,C16,D16,E16) -> 32
B17: Opening cash | C17: 18000000 | D17: 18000000 | E17: 18000000 | F17: $ | G17: 1-Jan-2026 cash balance | H17: =CHOOSE($H$4,C17,D17,E17) -> 18000000
... B23: Variance threshold $ | C23: 50000 | D23: 50000 | E23: 50000 | F23: $ | G23: Board materiality flag | H23: =CHOOSE($H$4,C23,D23,E23) -> 50000
G25: Selected scenario name | H25: =INDEX($K$3:$K$5,MATCH($H$4,$J$3:$J$5,0)) -> Base

Sheet Customer ARR Ledger
A1: Customer ARR Ledger | source data imported from CSV
A3: month | B3: customer_id | C3: plan_tier | D3: acquisition_channel | E3: sales_rep | F3: mrr | G3: status | H3: cohort_month | I3: prior_mrr | J3: mrr_movement
A4: 45292 | B4: CUST-1000 | C4: SMB | D4: Inbound | E4: Riley | F4: 1900 | G4: new | H4: 45292 | I4: 0 | J4: 1900
A5: 45292 | B5: CUST-1001 | C5: SMB | D5: Outbound | E5: Jamie | F5: 3200 | G5: new | H5: 45292 | I5: 0 | J5: 3200
A6: 45292 | B6: CUST-1002 | C6: SMB | D6: Outbound | E6: Taylor | F6: 2400 | G6: new | H6: 45292 | I6: 0 | J6: 2400
A7: 45292 | B7: CUST-1003 | C7: Mid-Market | D7: Inbound | E7: Casey | F7: 8300 | G7: new | H7: 45292 | I7: 0 | J7: 8300
A8: 45292 | B8: CUST-1004 | C8: SMB | D8: Outbound | E8: Riley | F8: 2100 | G8: new | H8: 45292 | I8: 0 | J8: 2100
A9: 45292 | B9: CUST-1005 | C9: Mid-Market | D9: Outbound | E9: Riley | F9: 7600 | G9: new | H9: 45292 | I9: 0 | J9: 7600
A10: 45292 | B10: CUST-1006 | C10: SMB | D10: Event | E10: Avery | F10: 3100 | G10: new | H10: 45292 | I10: 0 | J10: 3100
A11: 45292 | B11: CUST-1007 | C11: SMB | D11: Partner | E11: Casey | F11: 2500 | G11: new | H11: 45292 | I11: 0 | J11: 2500
A12: 45292 | B12: CUST-1008 | C12: SMB | D12: Outbound | E12: Morgan | F12: 1800 | G12: new | H12: 45292 | I12: 0 | J12: 1800
A13: 45292 | B13: CUST-1009 | C13: SMB | D13: Partner | E13: Jordan | F13: 3600 | G13: new | H13: 45292 | I13: 0 | J13: 3600
A14: 45292 | B14: CUST-1010 | C14: Mid-Market | D14: Partner | E14: Jamie | F14: 7700 | G14: new | H14: 45292 | I14: 0 | J14: 7700
A15: 45292 | B15: CUST-1011 | C15: Mid-Market | D15: Outbound | E15: Taylor | F15: 11400 | G15: new | H15: 45292 | I15: 0 | J15: 11400
... A10226: 46357 | B10226: CUST-1470 | C10226: SMB | D10226: Partner | E10226: Jamie | F10226: 2300 | G10226: new | H10226: 46357 | I10226: 0 | J10226: 2300

Sheet ARR Bridge
A1: ARR Bridge | beginning + new + expansion - contraction - churn = ending
C3: 46023 | D3: 46054 | E3: 46082 | F3: 46113 | G3: 46143 | H3: 46174 | I3: 46204 | J3: 46235 | K3: 46266 | L3: 46296 | M3: 46327 | N3: 46357
B4: Beginning ARR | C4: =IF(C$3=DATE(2026,1,1),SUMIFS('Customer ARR Ledger'!$F$4:$F$10226,'Customer ARR Ledger'!$A$4:$A$10226,DATE(2025,12,1))*12,B10) -> 48393600 | D4: =IF(D$3=DATE(2026,1,1),SUMIFS('Customer ARR Ledger'!$F$4:$F$10226,'Customer ARR Ledger'!$A$4:$A$10226,DATE(2025,12,1))*12,C10) -> 48380400 | E4: =IF(E$3=DATE(2026,1,1),SUMIFS('Customer ARR Ledger'!$F$4:$F$10226,'Customer ARR Ledger'!$A$4:$A$10226,DATE(2025,12,1))*12,D10) -> 47478000 | F4: =IF(F$3=DATE(2026,1,1),SUMIFS('Customer ARR Ledger'!$F$4:$F$10226,'Customer ARR Ledger'!$A$4:$A$10226,DATE(2025,12,1))*12,E10) -> 47031600 | G4: =IF(G$3=DATE(2026,1,1),SUMIFS('Customer ARR Ledger'!$F$4:$F$10226,'Customer ARR Ledger'!$A$4:$A$10226,DATE(2025,12,1))*12,F10) -> 48093600 | H4: =IF(H$3=DATE(2026,1,1),SUMIFS('Customer ARR Ledger'!$F$4:$F$10226,'Customer ARR Ledger'!$A$4:$A$10226,DATE(2025,12,1))*12,G10) -> 47923200 | I4: =IF(I$3=DATE(2026,1,1),SUMIFS('Customer ARR Ledger'!$F$4:$F$10226,'Customer ARR Ledger'!$A$4:$A$10226,DATE(2025,12,1))*12,H10) -> 48980400 | J4: =IF(J$3=DATE(2026,1,1),SUMIFS('Customer ARR Ledger'!$F$4:$F$10226,'Customer ARR Ledger'!$A$4:$A$10226,DATE(2025,12,1))*12,I10) -> 49276800 | ... N4: =IF(N$3=DATE(2026,1,1),SUMIFS('Customer ARR Ledger'!$F$4:$F$10226,'Customer ARR Ledger'!$A$4:$A$10226,DATE(2025,12,1))*12,M10) -> 51692400
B5: New ARR | C5: =SUMIFS('Customer ARR Ledger'!$J$4:$J$10226,'Customer ARR Ledger'!$A$4:$A$10226,C$3,'Customer ARR Ledger'!$G$4:$G$10226,"new")*12 -> 403200 | D5: =SUMIFS('Customer ARR Ledger'!$J$4:$J$10226,'Customer ARR Ledger'!$A$4:$A$10226,D$3,'Customer ARR Ledger'!$G$4:$G$10226,"new")*12 -> 1225200 | E5: =SUMIFS('Customer ARR Ledger'!$J$4:$J$10226,'Customer ARR Ledger'!$A$4:$A$10226,E$3,'Customer ARR Ledger'!$G$4:$G$10226,"new")*12 -> 564000 | F5: =SUMIFS('Customer ARR Ledger'!$J$4:$J$10226,'Customer ARR Ledger'!$A$4:$A$10226,F$3,'Customer ARR Ledger'!$G$4:$G$10226,"new")*12 -> 1141200 | G5: =SUMIFS('Customer ARR Ledger'!$J$4:$J$10226,'Customer ARR Ledger'!$A$4:$A$10226,G$3,'Customer ARR Ledger'!$G$4:$G$10226,"new")*12 -> 856800 | H5: =SUMIFS('Customer ARR Ledger'!$J$4:$J$10226,'Customer ARR Ledger'!$A$4:$A$10226,H$3,'Customer ARR Ledger'!$G$4:$G$10226,"new")*12 -> 1126800 | I5: =SUMIFS('Customer ARR Ledger'!$J$4:$J$10226,'Customer ARR Ledger'!$A$4:$A$10226,I$3,'Customer ARR Ledger'!$G$4:$G$10226,"new")*12 -> 642000 | J5: =SUMIFS('Customer ARR Ledger'!$J$4:$J$10226,'Customer ARR Ledger'!$A$4:$A$10226,J$3,'Customer ARR Ledger'!$G$4:$G$10226,"new")*12 -> 938400 | ... N5: =SUMIFS('Customer ARR Ledger'!$J$4:$J$10226,'Customer ARR Ledger'!$A$4:$A$10226,N$3,'Customer ARR Ledger'!$G$4:$G$10226,"new")*12 -> 507600
B6: Expansion ARR | C6: =SUMIFS('Customer ARR Ledger'!$J$4:$J$10226,'Customer ARR Ledger'!$A$4:$A$10226,C$3,'Customer ARR Ledger'!$G$4:$G$10226,"expanded")*12 -> 103200 | D6: =SUMIFS('Customer ARR Ledger'!$J$4:$J$10226,'Customer ARR Ledger'!$A$4:$A$10226,D$3,'Customer ARR Ledger'!$G$4:$G$10226,"expanded")*12 -> 18000 | E6: =SUMIFS('Customer ARR Ledger'!$J$4:$J$10226,'Customer ARR Ledger'!$A$4:$A$10226,E$3,'Customer ARR Ledger'!$G$4:$G$10226,"expanded")*12 -> 44400 | F6: =SUMIFS('Customer ARR Ledger'!$J$4:$J$10226,'Customer ARR Ledger'!$A$4:$A$10226,F$3,'Customer ARR Ledger'!$G$4:$G$10226,"expanded")*12 -> 170400 | G6: =SUMIFS('Customer ARR Ledger'!$J$4:$J$10226,'Customer ARR Ledger'!$A$4:$A$10226,G$3,'Customer ARR Ledger'!$G$4:$G$10226,"expanded")*12 -> 140400 | H6: =SUMIFS('Customer ARR Ledger'!$J$4:$J$10226,'Customer ARR Ledger'!$A$4:$A$10226,H$3,'Customer ARR Ledger'!$G$4:$G$10226,"expanded")*12 -> 192000 | I6: =SUMIFS('Customer ARR Ledger'!$J$4:$J$10226,'Customer ARR Ledger'!$A$4:$A$10226,I$3,'Customer ARR Ledger'!$G$4:$G$10226,"expanded")*12 -> 40800 | J6: =SUMIFS('Customer ARR Ledger'!$J$4:$J$10226,'Customer ARR Ledger'!$A$4:$A$10226,J$3,'Customer ARR Ledger'!$G$4:$G$10226,"expanded")*12 -> 52800 | ... N6: =SUMIFS('Customer ARR Ledger'!$J$4:$J$10226,'Customer ARR Ledger'!$A$4:$A$10226,N$3,'Customer ARR Ledger'!$G$4:$G$10226,"expanded")*12 -> 51600
B7: Contraction ARR | C7: =-SUMIFS('Customer ARR Ledger'!$J$4:$J$10226,'Customer ARR Ledger'!$A$4:$A$10226,C$3,'Customer ARR Ledger'!$G$4:$G$10226,"contracted")*12 -> 43200 | D7: =-SUMIFS('Customer ARR Ledger'!$J$4:$J$10226,'Customer ARR Ledger'!$A$4:$A$10226,D$3,'Customer ARR Ledger'!$G$4:$G$10226,"contracted")*12 -> 279600 | E7: =-SUMIFS('Customer ARR Ledger'!$J$4:$J$10226,'Customer ARR Ledger'!$A$4:$A$10226,E$3,'Customer ARR Ledger'!$G$4:$G$10226,"contracted")*12 -> 79200 | F7: =-SUMIFS('Customer ARR Ledger'!$J$4:$J$10226,'Customer ARR Ledger'!$A$4:$A$10226,F$3,'Customer ARR Ledger'!$G$4:$G$10226,"contracted")*12 -> 94800 | G7: =-SUMIFS('Customer ARR Ledger'!$J$4:$J$10226,'Customer ARR Ledger'!$A$4:$A$10226,G$3,'Customer ARR Ledger'!$G$4:$G$10226,"contracted")*12 -> 39600 | H7: =-SUMIFS('Customer ARR Ledger'!$J$4:$J$10226,'Customer ARR Ledger'!$A$4:$A$10226,H$3,'Customer ARR Ledger'!$G$4:$G$10226,"contracted")*12 -> 64800 | I7: =-SUMIFS('Customer ARR Ledger'!$J$4:$J$10226,'Customer ARR Ledger'!$A$4:$A$10226,I$3,'Customer ARR Ledger'!$G$4:$G$10226,"contracted")*12 -> 344400 | J7: =-SUMIFS('Customer ARR Ledger'!$J$4:$J$10226,'Customer ARR Ledger'!$A$4:$A$10226,J$3,'Customer ARR Ledger'!$G$4:$G$10226,"contracted")*12 -> 10800 | ... N7: =-SUMIFS('Customer ARR Ledger'!$J$4:$J$10226,'Customer ARR Ledger'!$A$4:$A$10226,N$3,'Customer ARR Ledger'!$G$4:$G$10226,"contracted")*12 -> 49200
B8: Churn ARR | C8: =-SUMIFS('Customer ARR Ledger'!$J$4:$J$10226,'Customer ARR Ledger'!$A$4:$A$10226,C$3,'Customer ARR Ledger'!$G$4:$G$10226,"churned")*12 -> 476400 | D8: =-SUMIFS('Customer ARR Ledger'!$J$4:$J$10226,'Customer ARR Ledger'!$A$4:$A$10226,D$3,'Customer ARR Ledger'!$G$4:$G$10226,"churned")*12 -> 1866000 | E8: =-SUMIFS('Customer ARR Ledger'!$J$4:$J$10226,'Customer ARR Ledger'!$A$4:$A$10226,E$3,'Customer ARR Ledger'!$G$4:$G$10226,"churned")*12 -> 975600 | F8: =-SUMIFS('Customer ARR Ledger'!$J$4:$J$10226,'Customer ARR Ledger'!$A$4:$A$10226,F$3,'Customer ARR Ledger'!$G$4:$G$10226,"churned")*12 -> 154800 | G8: =-SUMIFS('Customer ARR Ledger'!$J$4:$J$10226,'Customer ARR Ledger'!$A$4:$A$10226,G$3,'Customer ARR Ledger'!$G$4:$G$10226,"churned")*12 -> 1128000 | H8: =-SUMIFS('Customer ARR Ledger'!$J$4:$J$10226,'Customer ARR Ledger'!$A$4:$A$10226,H$3,'Customer ARR Ledger'!$G$4:$G$10226,"churned")*12 -> 196800 | I8: =-SUMIFS('Customer ARR Ledger'!$J$4:$J$10226,'Customer ARR Ledger'!$A$4:$A$10226,I$3,'Customer ARR Ledger'!$G$4:$G$10226,"churned")*12 -> 42000 | J8: =-SUMIFS('Customer ARR Ledger'!$J$4:$J$10226,'Customer ARR Ledger'!$A$4:$A$10226,J$3,'Customer ARR Ledger'!$G$4:$G$10226,"churned")*12 -> 1004400 | ... N8: =-SUMIFS('Customer ARR Ledger'!$J$4:$J$10226,'Customer ARR Ledger'!$A$4:$A$10226,N$3,'Customer ARR Ledger'!$G$4:$G$10226,"churned")*12 -> 151200
B9: Net New ARR | C9: =SUM(C5:C6)-SUM(C7:C8) -> -13200 | D9: =SUM(D5:D6)-SUM(D7:D8) -> -902400 | E9: =SUM(E5:E6)-SUM(E7:E8) -> -446400 | F9: =SUM(F5:F6)-SUM(F7:F8) -> 1062000 | G9: =SUM(G5:G6)-SUM(G7:G8) -> -170400 | H9: =SUM(H5:H6)-SUM(H7:H8) -> 1057200 | I9: =SUM(I5:I6)-SUM(I7:I8) -> 296400 | J9: =SUM(J5:J6)-SUM(J7:J8) -> -24000 | ... N9: =SUM(N5:N6)-SUM(N7:N8) -> 358800
B10: Ending ARR | C10: =SUM(C4:C6)-SUM(C7:C8) -> 48380400 | D10: =SUM(D4:D6)-SUM(D7:D8) -> 47478000 | E10: =SUM(E4:E6)-SUM(E7:E8) -> 47031600 | F10: =SUM(F4:F6)-SUM(F7:F8) -> 48093600 | G10: =SUM(G4:G6)-SUM(G7:G8) -> 47923200 | H10: =SUM(H4:H6)-SUM(H7:H8) -> 48980400 | I10: =SUM(I4:I6)-SUM(I7:I8) -> 49276800 | J10: =SUM(J4:J6)-SUM(J7:J8) -> 49252800 | ... N10: =SUM(N4:N6)-SUM(N7:N8) -> 52051200
B11: Bridge Check | C11: =C10-(SUMIFS('Customer ARR Ledger'!$F$4:$F$10226,'Customer ARR Ledger'!$A$4:$A$10226,C$3)*12) -> 0 | D11: =D10-(SUMIFS('Customer ARR Ledger'!$F$4:$F$10226,'Customer ARR Ledger'!$A$4:$A$10226,D$3)*12) -> 0 | E11: =E10-(SUMIFS('Customer ARR Ledger'!$F$4:$F$10226,'Customer ARR Ledger'!$A$4:$A$10226,E$3)*12) -> 0 | F11: =F10-(SUMIFS('Customer ARR Ledger'!$F$4:$F$10226,'Customer ARR Ledger'!$A$4:$A$10226,F$3)*12) -> 0 | G11: =G10-(SUMIFS('Customer ARR Ledger'!$F$4:$F$10226,'Customer ARR Ledger'!$A$4:$A$10226,G$3)*12) -> 0 | H11: =H10-(SUMIFS('Customer ARR Ledger'!$F$4:$F$10226,'Customer ARR Ledger'!$A$4:$A$10226,H$3)*12) -> 0 | I11: =I10-(SUMIFS('Customer ARR Ledger'!$F$4:$F$10226,'Customer ARR Ledger'!$A$4:$A$10226,I$3)*12) -> 0 | J11: =J10-(SUMIFS('Customer ARR Ledger'!$F$4:$F$10226,'Customer ARR Ledger'!$A$4:$A$10226,J$3)*12) -> 0 | ... N11: =N10-(SUMIFS('Customer ARR Ledger'!$F$4:$F$10226,'Customer ARR Ledger'!$A$4:$A$10226,N$3)*12) -> 0

Sheet Revenue Forecast
A1: Revenue Forecast | driver-based Base / Upside / Downside
C3: 46023 | D3: 46054 | E3: 46082 | F3: 46113 | G3: 46143 | H3: 46174 | I3: 46204 | J3: 46235 | K3: 46266 | L3: 46296 | M3: 46327 | N3: 46357
B4: Base
B5: Beginning ARR | C5: =IF(C$3=DATE(2026,1,1),'ARR Bridge'!C4,B10) -> 48393600 | D5: =IF(D$3=DATE(2026,1,1),'ARR Bridge'!C4,C10) -> 49019718 | E5: =IF(E$3=DATE(2026,1,1),'ARR Bridge'!C4,D10) -> 49538266 | F5: =IF(F$3=DATE(2026,1,1),'ARR Bridge'!C4,E10) -> 50610694 | G5: =IF(G$3=DATE(2026,1,1),'ARR Bridge'!C4,F10) -> 51033607 | H5: =IF(H$3=DATE(2026,1,1),'ARR Bridge'!C4,G10) -> 51365761 | I5: =IF(I$3=DATE(2026,1,1),'ARR Bridge'!C4,H10) -> 51998343 | J5: =IF(J$3=DATE(2026,1,1),'ARR Bridge'!C4,I10) -> 53044539 | K5: =IF(K$3=DATE(2026,1,1),'ARR Bridge'!C4,J10) -> 53323307 | L5: =IF(L$3=DATE(2026,1,1),'ARR Bridge'!C4,K10) -> 55132034 | M5: =IF(M$3=DATE(2026,1,1),'ARR Bridge'!C4,L10) -> 55462875 | N5: =IF(N$3=DATE(2026,1,1),'ARR Bridge'!C4,M10) -> 56218361
B6: Pipeline New ARR | C6: =SUMIFS($Y$39:$Y$458,$Z$39:$Z$458,C$3)*Assumptions!C8 -> 940676 | D6: =SUMIFS($Y$39:$Y$458,$Z$39:$Z$458,D$3)*Assumptions!C8 -> 837177 | E6: =SUMIFS($Y$39:$Y$458,$Z$39:$Z$458,E$3)*Assumptions!C8 -> 1394426 | F6: =SUMIFS($Y$39:$Y$458,$Z$39:$Z$458,F$3)*Assumptions!C8 -> 751883 | G6: =SUMIFS($Y$39:$Y$458,$Z$39:$Z$458,G$3)*Assumptions!C8 -> 663872 | H6: =SUMIFS($Y$39:$Y$458,$Z$39:$Z$458,H$3)*Assumptions!C8 -> 966460 | I6: =SUMIFS($Y$39:$Y$458,$Z$39:$Z$458,I$3)*Assumptions!C8 -> 1384185 | J6: =SUMIFS($Y$39:$Y$458,$Z$39:$Z$458,J$3)*Assumptions!C8 -> 623557 | K6: =SUMIFS($Y$39:$Y$458,$Z$39:$Z$458,K$3)*Assumptions!C8 -> 2155329 | L6: =SUMIFS($Y$39:$Y$458,$Z$39:$Z$458,L$3)*Assumptions!C8 -> 689199.5 | M6: =SUMIFS($Y$39:$Y$458,$Z$39:$Z$458,M$3)*Assumptions!C8 -> 1115994 | N6: =SUMIFS($Y$39:$Y$458,$Z$39:$Z$458,N$3)*Assumptions!C8 -> 2411310
B7: Expansion ARR | C7: =C5*Assumptions!C6 -> 314558.4 | D7: =D5*Assumptions!C6 -> 318628.16 | E7: =E5*Assumptions!C6 -> 321998.73 | F7: =F5*Assumptions!C6 -> 328969.51 | G7: =G5*Assumptions!C6 -> 331718.45 | H7: =H5*Assumptions!C6 -> 333877.44 | I7: =I5*Assumptions!C6 -> 337989.23 | J7: =J5*Assumptions!C6 -> 344789.5 | K7: =K5*Assumptions!C6 -> 346601.49 | L7: =L5*Assumptions!C6 -> 358358.22 | M7: =M5*Assumptions!C6 -> 360508.69 | N7: =N5*Assumptions!C6 -> 365419.34
B8: Contraction ARR | C8: =C5*Assumptions!C7 -> 96787.2 | D8: =D5*Assumptions!C7 -> 98039.435 | E8: =E5*Assumptions!C7 -> 99076.533 | F8: =F5*Assumptions!C7 -> 101221.39 | G8: =G5*Assumptions!C7 -> 102067.21 | H8: =H5*Assumptions!C7 -> 102731.52 | I8: =I5*Assumptions!C7 -> 103996.69 | J8: =J5*Assumptions!C7 -> 106089.08 | K8: =K5*Assumptions!C7 -> 106646.61 | L8: =L5*Assumptions!C7 -> 110264.07 | M8: =M5*Assumptions!C7 -> 110925.75 | N8: =N5*Assumptions!C7 -> 112436.72
B9: Churn ARR | C9: =C5*Assumptions!C5 -> 532329.6 | D9: =D5*Assumptions!C5 -> 539216.89 | E9: =E5*Assumptions!C5 -> 544920.93 | F9: =F5*Assumptions!C5 -> 556717.63 | G9: =G5*Assumptions!C5 -> 561369.68 | H9: =H5*Assumptions!C5 -> 565023.37 | I9: =I5*Assumptions!C5 -> 571981.78 | J9: =J5*Assumptions!C5 -> 583489.93 | K9: =K5*Assumptions!C5 -> 586556.37 | L9: =L5*Assumptions!C5 -> 606452.37 | M9: =M5*Assumptions!C5 -> 610091.63 | N9: =N5*Assumptions!C5 -> 618401.97
B10: Ending ARR | C10: =SUM(C5:C7)-SUM(C8:C9) -> 49019718 | D10: =SUM(D5:D7)-SUM(D8:D9) -> 49538266 | E10: =SUM(E5:E7)-SUM(E8:E9) -> 50610694 | F10: =SUM(F5:F7)-SUM(F8:F9) -> 51033607 | G10: =SUM(G5:G7)-SUM(G8:G9) -> 51365761 | H10: =SUM(H5:H7)-SUM(H8:H9) -> 51998343 | I10: =SUM(I5:I7)-SUM(I8:I9) -> 53044539 | J10: =SUM(J5:J7)-SUM(J8:J9) -> 53323307 | ... N10: =SUM(N5:N7)-SUM(N8:N9) -> 58264251
B11: Recognized Revenue | C11: =AVERAGE(C5,C10)/12 -> 4058888.2 | D11: =AVERAGE(D5,D10)/12 -> 4106582.7 | E11: =AVERAGE(E5,E10)/12 -> 4172873.3 | F11: =AVERAGE(F5,F10)/12 -> 4235179.2 | G11: =AVERAGE(G5,G10)/12 -> 4266640.3 | H11: =AVERAGE(H5,H10)/12 -> 4306837.7 | I11: =AVERAGE(I5,I10)/12 -> 4376786.8 | J11: =AVERAGE(J5,J10)/12 -> 4431993.6 | ... N11: =AVERAGE(N5,N10)/12 -> 4770108.8
B13: Upside
B14: Beginning ARR | C14: =IF(C$3=DATE(2026,1,1),'ARR Bridge'!C4,B19) -> 48393600 | D14: =IF(D$3=DATE(2026,1,1),'ARR Bridge'!C4,C19) -> 49547270 | E14: =IF(E$3=DATE(2026,1,1),'ARR Bridge'!C4,D19) -> 50568175 | F14: =IF(F$3=DATE(2026,1,1),'ARR Bridge'!C4,E19) -> 52297388 | G14: =IF(G$3=DATE(2026,1,1),'ARR Bridge'!C4,F19) -> 53207262 | H14: =IF(H$3=DATE(2026,1,1),'ARR Bridge'!C4,G19) -> 54004304 | I14: =IF(I$3=DATE(2026,1,1),'ARR Bridge'!C4,H19) -> 55185740 | J14: =IF(J$3=DATE(2026,1,1),'ARR Bridge'!C4,I19) -> 56897763 | K14: =IF(K$3=DATE(2026,1,1),'ARR Bridge'!C4,J19) -> 57640173 | L14: =IF(L$3=DATE(2026,1,1),'ARR Bridge'!C4,K19) -> 60331442 | M14: =IF(M$3=DATE(2026,1,1),'ARR Bridge'!C4,L19) -> 61154307 | N14: =IF(N$3=DATE(2026,1,1),'ARR Bridge'!C4,M19) -> 62519624
B15: Pipeline New ARR | C15: =SUMIFS($Y$39:$Y$458,$Z$39:$Z$458,C$3)*Assumptions!D8 -> 1197224 | D15: =SUMIFS($Y$39:$Y$458,$Z$39:$Z$458,D$3)*Assumptions!D8 -> 1065498 | E15: =SUMIFS($Y$39:$Y$458,$Z$39:$Z$458,E$3)*Assumptions!D8 -> 1774724 | F15: =SUMIFS($Y$39:$Y$458,$Z$39:$Z$458,F$3)*Assumptions!D8 -> 956942 | G15: =SUMIFS($Y$39:$Y$458,$Z$39:$Z$458,G$3)*Assumptions!D8 -> 844928 | H15: =SUMIFS($Y$39:$Y$458,$Z$39:$Z$458,H$3)*Assumptions!D8 -> 1230040 | I15: =SUMIFS($Y$39:$Y$458,$Z$39:$Z$458,I$3)*Assumptions!D8 -> 1761690 | J15: =SUMIFS($Y$39:$Y$458,$Z$39:$Z$458,J$3)*Assumptions!D8 -> 793618 | K15: =SUMIFS($Y$39:$Y$458,$Z$39:$Z$458,K$3)*Assumptions!D8 -> 2743146 | L15: =SUMIFS($Y$39:$Y$458,$Z$39:$Z$458,L$3)*Assumptions!D8 -> 877163 | M15: =SUMIFS($Y$39:$Y$458,$Z$39:$Z$458,M$3)*Assumptions!D8 -> 1420356 | N15: =SUMIFS($Y$39:$Y$458,$Z$39:$Z$458,N$3)*Assumptions!D8 -> 3068940
B16: Expansion ARR | C16: =C14*Assumptions!D6 -> 411345.6 | D16: =D14*Assumptions!D6 -> 421151.79 | E16: =E14*Assumptions!D6 -> 429829.49 | F16: =F14*Assumptions!D6 -> 444527.8 | G16: =G14*Assumptions!D6 -> 452261.73 | H16: =H14*Assumptions!D6 -> 459036.58 | I16: =I14*Assumptions!D6 -> 469078.79 | J16: =J14*Assumptions!D6 -> 483630.98 | K16: =K14*Assumptions!D6 -> 489941.47 | L16: =L14*Assumptions!D6 -> 512817.26 | M16: =M14*Assumptions!D6 -> 519811.61 | N16: =N14*Assumptions!D6 -> 531416.81
B17: Contraction ARR | C17: =C14*Assumptions!D7 -> 67751.04 | D17: =D14*Assumptions!D7 -> 69366.178 | E17: =E14*Assumptions!D7 -> 70795.445 | F17: =F14*Assumptions!D7 -> 73216.343 | G17: =G14*Assumptions!D7 -> 74490.167 | H17: =H14*Assumptions!D7 -> 75606.025 | I17: =I14*Assumptions!D7 -> 77260.036 | J17: =J14*Assumptions!D7 -> 79656.868 | K17: =K14*Assumptions!D7 -> 80696.242 | L17: =L14*Assumptions!D7 -> 84464.019 | M17: =M14*Assumptions!D7 -> 85616.03 | N17: =N14*Assumptions!D7 -> 87527.474
B18: Churn ARR | C18: =C14*Assumptions!D5 -> 387148.8 | D18: =D14*Assumptions!D5 -> 396378.16 | E18: =E14*Assumptions!D5 -> 404545.4 | F18: =F14*Assumptions!D5 -> 418379.1 | G18: =G14*Assumptions!D5 -> 425658.1 | H18: =H14*Assumptions!D5 -> 432034.43 | I18: =I14*Assumptions!D5 -> 441485.92 | J18: =J14*Assumptions!D5 -> 455182.1 | K18: =K14*Assumptions!D5 -> 461121.38 | L18: =L14*Assumptions!D5 -> 482651.54 | M18: =M14*Assumptions!D5 -> 489234.46 | N18: =N14*Assumptions!D5 -> 500156.99
B19: Ending ARR | C19: =SUM(C14:C16)-SUM(C17:C18) -> 49547270 | D19: =SUM(D14:D16)-SUM(D17:D18) -> 50568175 | E19: =SUM(E14:E16)-SUM(E17:E18) -> 52297388 | F19: =SUM(F14:F16)-SUM(F17:F18) -> 53207262 | G19: =SUM(G14:G16)-SUM(G17:G18) -> 54004304 | H19: =SUM(H14:H16)-SUM(H17:H18) -> 55185740 | I19: =SUM(I14:I16)-SUM(I17:I18) -> 56897763 | J19: =SUM(J14:J16)-SUM(J17:J18) -> 57640173 | ... N19: =SUM(N14:N16)-SUM(N17:N18) -> 65532297
B20: Recognized Revenue | C20: =AVERAGE(C14,C19)/12 -> 4080869.6 | D20: =AVERAGE(D14,D19)/12 -> 4171476.9 | E20: =AVERAGE(E14,E19)/12 -> 4286065.1 | F20: =AVERAGE(F14,F19)/12 -> 4396027.1 | G20: =AVERAGE(G14,G19)/12 -> 4467148.6 | H20: =AVERAGE(H14,H19)/12 -> 4549585.1 | I20: =AVERAGE(I14,I19)/12 -> 4670145.9 | J20: =AVERAGE(J14,J19)/12 -> 4772414 | ... N20: =AVERAGE(N14,N19)/12 -> 5335496.7
B22: Downside
B23: Beginning ARR | C23: =IF(C$3=DATE(2026,1,1),'ARR Bridge'!C4,B28) -> 48393600 | D23: =IF(D$3=DATE(2026,1,1),'ARR Bridge'!C4,C28) -> 48307939 | E23: =IF(E$3=DATE(2026,1,1),'ARR Bridge'!C4,D28) -> 48152071 | F23: =IF(F$3=DATE(2026,1,1),'ARR Bridge'!C4,E28) -> 48383582 | G23: =IF(G$3=DATE(2026,1,1),'ARR Bridge'!C4,F28) -> 48167634 | H23: =IF(H$3=DATE(2026,1,1),'ARR Bridge'!C4,G28) -> 47894161 | I23: =IF(I$3=DATE(2026,1,1),'ARR Bridge'!C4,H28) -> 47833906 | J23: =IF(J$3=DATE(2026,1,1),'ARR Bridge'!C4,I28) -> 48063176 | K23: =IF(K$3=DATE(2026,1,1),'ARR Bridge'!C4,J28) -> 47763437 | L23: =IF(L$3=DATE(2026,1,1),'ARR Bridge'!C4,K28) -> 48526570 | M23: =IF(M$3=DATE(2026,1,1),'ARR Bridge'!C4,L28) -> 48265140 | N23: =IF(N$3=DATE(2026,1,1),'ARR Bridge'!C4,M28) -> 48302560
B24: Pipeline New ARR | C24: =SUMIFS($Y$39:$Y$458,$Z$39:$Z$458,C$3)*Assumptions!E8 -> 649921.6 | D24: =SUMIFS($Y$39:$Y$458,$Z$39:$Z$458,D$3)*Assumptions!E8 -> 578413.2 | E24: =SUMIFS($Y$39:$Y$458,$Z$39:$Z$458,E$3)*Assumptions!E8 -> 963421.6 | F24: =SUMIFS($Y$39:$Y$458,$Z$39:$Z$458,F$3)*Assumptions!E8 -> 519482.8 | G24: =SUMIFS($Y$39:$Y$458,$Z$39:$Z$458,G$3)*Assumptions!E8 -> 458675.2 | H24: =SUMIFS($Y$39:$Y$458,$Z$39:$Z$458,H$3)*Assumptions!E8 -> 667736 | I24: =SUMIFS($Y$39:$Y$458,$Z$39:$Z$458,I$3)*Assumptions!E8 -> 956346 | J24: =SUMIFS($Y$39:$Y$458,$Z$39:$Z$458,J$3)*Assumptions!E8 -> 430821.2 | K24: =SUMIFS($Y$39:$Y$458,$Z$39:$Z$458,K$3)*Assumptions!E8 -> 1489136.4 | L24: =SUMIFS($Y$39:$Y$458,$Z$39:$Z$458,L$3)*Assumptions!E8 -> 476174.2 | M24: =SUMIFS($Y$39:$Y$458,$Z$39:$Z$458,M$3)*Assumptions!E8 -> 771050.4 | N24: =SUMIFS($Y$39:$Y$458,$Z$39:$Z$458,N$3)*Assumptions!E8 -> 1665996
B25: Expansion ARR | C25: =C23*Assumptions!E6 -> 193574.4 | D25: =D23*Assumptions!E6 -> 193231.76 | E25: =E23*Assumptions!E6 -> 192608.29 | F25: =F23*Assumptions!E6 -> 193534.33 | G25: =G23*Assumptions!E6 -> 192670.54 | H25: =H23*Assumptions!E6 -> 191576.64 | I25: =I23*Assumptions!E6 -> 191335.62 | J25: =J23*Assumptions!E6 -> 192252.71 | K25: =K23*Assumptions!E6 -> 191053.75 | L25: =L23*Assumptions!E6 -> 194106.28 | M25: =M23*Assumptions!E6 -> 193060.56 | N25: =N23*Assumptions!E6 -> 193210.24
B26: Contraction ARR | C26: =C23*Assumptions!E7 -> 154859.52 | D26: =D23*Assumptions!E7 -> 154585.4 | E26: =E23*Assumptions!E7 -> 154086.63 | F26: =F23*Assumptions!E7 -> 154827.46 | G26: =G23*Assumptions!E7 -> 154136.43 | H26: =H23*Assumptions!E7 -> 153261.32 | I26: =I23*Assumptions!E7 -> 153068.5 | J26: =J23*Assumptions!E7 -> 153802.16 | K26: =K23*Assumptions!E7 -> 152843 | L26: =L23*Assumptions!E7 -> 155285.02 | M26: =M23*Assumptions!E7 -> 154448.45 | N26: =N23*Assumptions!E7 -> 154568.19
B27: Churn ARR | C27: =C23*Assumptions!E5 -> 774297.6 | D27: =D23*Assumptions!E5 -> 772927.02 | E27: =E23*Assumptions!E5 -> 770433.14 | F27: =F23*Assumptions!E5 -> 774137.3 | G27: =G23*Assumptions!E5 -> 770682.14 | H27: =H23*Assumptions!E5 -> 766306.58 | I27: =I23*Assumptions!E5 -> 765342.49 | J27: =J23*Assumptions!E5 -> 769010.82 | K27: =K23*Assumptions!E5 -> 764215 | L27: =L23*Assumptions!E5 -> 776425.11 | M27: =M23*Assumptions!E5 -> 772242.24 | N27: =N23*Assumptions!E5 -> 772840.96
B28: Ending ARR | C28: =SUM(C23:C25)-SUM(C26:C27) -> 48307939 | D28: =SUM(D23:D25)-SUM(D26:D27) -> 48152071 | E28: =SUM(E23:E25)-SUM(E26:E27) -> 48383582 | F28: =SUM(F23:F25)-SUM(F26:F27) -> 48167634 | G28: =SUM(G23:G25)-SUM(G26:G27) -> 47894161 | H28: =SUM(H23:H25)-SUM(H26:H27) -> 47833906 | I28: =SUM(I23:I25)-SUM(I26:I27) -> 48063176 | J28: =SUM(J23:J25)-SUM(J26:J27) -> 47763437 | ... N28: =SUM(N23:N25)-SUM(N26:N27) -> 49234357
B29: Recognized Revenue | C29: =AVERAGE(C23,C28)/12 -> 4029230.8 | D29: =AVERAGE(D23,D28)/12 -> 4019167.1 | E29: =AVERAGE(E23,E28)/12 -> 4022318.9 | F29: =AVERAGE(F23,F28)/12 -> 4022967.3 | G29: =AVERAGE(G23,G28)/12 -> 4002574.8 | H29: =AVERAGE(H23,H28)/12 -> 3988669.5 | I29: =AVERAGE(I23,I28)/12 -> 3995711.8 | J29: =AVERAGE(J23,J28)/12 -> 3992775.6 | ... N29: =AVERAGE(N23,N28)/12 -> 4064038.2
B32: Selected Scenario Output
B33: Selected Revenue | C33: =CHOOSE(Scenario_Select,C11,C20,C29) -> 4058888.2 | D33: =CHOOSE(Scenario_Select,D11,D20,D29) -> 4106582.7 | E33: =CHOOSE(Scenario_Select,E11,E20,E29) -> 4172873.3 | F33: =CHOOSE(Scenario_Select,F11,F20,F29) -> 4235179.2 | G33: =CHOOSE(Scenario_Select,G11,G20,G29) -> 4266640.3 | H33: =CHOOSE(Scenario_Select,H11,H20,H29) -> 4306837.7 | I33: =CHOOSE(Scenario_Select,I11,I20,I29) -> 4376786.8 | J33: =CHOOSE(Scenario_Select,J11,J20,J29) -> 4431993.6 | ... N33: =CHOOSE(Scenario_Select,N11,N20,N29) -> 4770108.8
B34: Selected Ending ARR | C34: =CHOOSE(Scenario_Select,C10,C19,C28) -> 49019718 | D34: =CHOOSE(Scenario_Select,D10,D19,D28) -> 49538266 | E34: =CHOOSE(Scenario_Select,E10,E19,E28) -> 50610694 | F34: =CHOOSE(Scenario_Select,F10,F19,F28) -> 51033607 | G34: =CHOOSE(Scenario_Select,G10,G19,G28) -> 51365761 | H34: =CHOOSE(Scenario_Select,H10,H19,H28) -> 51998343 | I34: =CHOOSE(Scenario_Select,I10,I19,I28) -> 53044539 | J34: =CHOOSE(Scenario_Select,J10,J19,J28) -> 53323307 | ... N34: =CHOOSE(Scenario_Select,N10,N19,N28) -> 58264251
P38: deal_id | Q38: stage | R38: probability | S38: deal_size | T38: expected_close_date | U38: sales_rep | V38: segment | W38: acquisition_channel | X38: sales_cycle_days
P39: DEAL-2000 | Q39: Negotiation | R39: 0.8 | S39: 159000 | T39: 46327 | U39: Jordan | V39: Mid-Market | W39: Outbound | X39: 83 | Y39: =R39*S39 -> 127200 | Z39: =DATE(YEAR(T39),MONTH(T39),1) -> 46327
P40: DEAL-2001 | Q40: Demo | R40: 0.3 | S40: 82000 | T40: 46327 | U40: Jamie | V40: Mid-Market | W40: Partner | X40: 85 | Y40: =R40*S40 -> 24600 | Z40: =DATE(YEAR(T40),MONTH(T40),1) -> 46327
P41: DEAL-2002 | Q41: Discovery | R41: 0.15 | S41: 44000 | T41: 46143 | U41: Casey | V41: SMB | W41: Outbound | X41: 54 | Y41: =R41*S41 -> 6600 | Z41: =DATE(YEAR(T41),MONTH(T41),1) -> 46143
P42: DEAL-2003 | Q42: Proposal | R42: 0.65 | S42: 30000 | T42: 46357 | U42: Jamie | V42: SMB | W42: Outbound | X42: 81 | Y42: =R42*S42 -> 19500 | Z42: =DATE(YEAR(T42),MONTH(T42),1) -> 46357
P43: DEAL-2004 | Q43: Evaluation | R43: 0.5 | S43: 120000 | T43: 46266 | U43: Taylor | V43: Mid-Market | W43: Inbound | X43: 69 | Y43: =R43*S43 -> 60000 | Z43: =DATE(YEAR(T43),MONTH(T43),1) -> 46266
P44: DEAL-2005 | Q44: Demo | R44: 0.3 | S44: 29000 | T44: 46296 | U44: Casey | V44: SMB | W44: Inbound | X44: 42 | Y44: =R44*S44 -> 8700 | Z44: =DATE(YEAR(T44),MONTH(T44),1) -> 46296
P45: DEAL-2006 | Q45: Demo | R45: 0.3 | S45: 451000 | T45: 46266 | U45: Jamie | V45: Enterprise | W45: Outbound | X45: 105 | Y45: =R45*S45 -> 135300 | Z45: =DATE(YEAR(T45),MONTH(T45),1) -> 46266
P46: DEAL-2007 | Q46: Evaluation | R46: 0.5 | S46: 88000 | T46: 46174 | U46: Morgan | V46: Mid-Market | W46: Outbound | X46: 78 | Y46: =R46*S46 -> 44000 | Z46: =DATE(YEAR(T46),MONTH(T46),1) -> 46174
P47: DEAL-2008 | Q47: Discovery | R47: 0.15 | S47: 259000 | T47: 46082 | U47: Jamie | V47: Enterprise | W47: Outbound | X47: 122 | Y47: =R47*S47 -> 38850 | Z47: =DATE(YEAR(T47),MONTH(T47),1) -> 46082
P48: DEAL-2009 | Q48: Commit | R48: 0.92 | S48: 88000 | T48: 46174 | U48: Taylor | V48: Mid-Market | W48: Partner | X48: 73 | Y48: =R48*S48 -> 80960 | Z48: =DATE(YEAR(T48),MONTH(T48),1) -> 46174
P49: DEAL-2010 | Q49: Evaluation | R49: 0.5 | S49: 105000 | T49: 46054 | U49: Casey | V49: Mid-Market | W49: Event | X49: 95 | Y49: =R49*S49 -> 52500 | Z49: =DATE(YEAR(T49),MONTH(T49),1) -> 46054
P50: DEAL-2011 | Q50: Evaluation | R50: 0.5 | S50: 30000 | T50: 46023 | U50: Jordan | V50: SMB | W50: Outbound | X50: 37 | Y50: =R50*S50 -> 15000 | Z50: =DATE(YEAR(T50),MONTH(T50),1) -> 46023
... P458: DEAL-2419 | Q458: Negotiation | R458: 0.8 | S458: 45000 | T458: 46174 | U458: Morgan | V458: SMB | W458: Outbound | X458: 60 | Y458: =R458*S458 -> 36000 | Z458: =DATE(YEAR(T458),MONTH(T458),1) -> 46174

Sheet Headcount & Opex Plan
A1: Headcount & Opex Plan | department build linked to Income Statement
C3: 46023 | D3: 46054 | E3: 46082 | F3: 46113 | G3: 46143 | H3: 46174 | I3: 46204 | J3: 46235 | K3: 46266 | L3: 46296 | M3: 46327 | N3: 46357
B4: Sales Headcount | C4: =SUMIFS($U$32:$U$499,$P$32:$P$499,C$3,$Q$32:$Q$499,"Sales")*Hiring_Pace -> 71 | D4: =SUMIFS($U$32:$U$499,$P$32:$P$499,D$3,$Q$32:$Q$499,"Sales")*Hiring_Pace -> 71 | E4: =SUMIFS($U$32:$U$499,$P$32:$P$499,E$3,$Q$32:$Q$499,"Sales")*Hiring_Pace -> 71 | F4: =SUMIFS($U$32:$U$499,$P$32:$P$499,F$3,$Q$32:$Q$499,"Sales")*Hiring_Pace -> 72 | G4: =SUMIFS($U$32:$U$499,$P$32:$P$499,G$3,$Q$32:$Q$499,"Sales")*Hiring_Pace -> 73 | H4: =SUMIFS($U$32:$U$499,$P$32:$P$499,H$3,$Q$32:$Q$499,"Sales")*Hiring_Pace -> 73 | I4: =SUMIFS($U$32:$U$499,$P$32:$P$499,I$3,$Q$32:$Q$499,"Sales")*Hiring_Pace -> 74 | J4: =SUMIFS($U$32:$U$499,$P$32:$P$499,J$3,$Q$32:$Q$499,"Sales")*Hiring_Pace -> 71 | ... N4: =SUMIFS($U$32:$U$499,$P$32:$P$499,N$3,$Q$32:$Q$499,"Sales")*Hiring_Pace -> 68
B5: Customer Success Headcount | C5: =SUMIFS($U$32:$U$499,$P$32:$P$499,C$3,$Q$32:$Q$499,"Customer Success")*Hiring_Pace -> 32 | D5: =SUMIFS($U$32:$U$499,$P$32:$P$499,D$3,$Q$32:$Q$499,"Customer Success")*Hiring_Pace -> 32 | E5: =SUMIFS($U$32:$U$499,$P$32:$P$499,E$3,$Q$32:$Q$499,"Customer Success")*Hiring_Pace -> 32 | F5: =SUMIFS($U$32:$U$499,$P$32:$P$499,F$3,$Q$32:$Q$499,"Customer Success")*Hiring_Pace -> 32 | G5: =SUMIFS($U$32:$U$499,$P$32:$P$499,G$3,$Q$32:$Q$499,"Customer Success")*Hiring_Pace -> 32 | H5: =SUMIFS($U$32:$U$499,$P$32:$P$499,H$3,$Q$32:$Q$499,"Customer Success")*Hiring_Pace -> 32 | I5: =SUMIFS($U$32:$U$499,$P$32:$P$499,I$3,$Q$32:$Q$499,"Customer Success")*Hiring_Pace -> 33 | J5: =SUMIFS($U$32:$U$499,$P$32:$P$499,J$3,$Q$32:$Q$499,"Customer Success")*Hiring_Pace -> 31 | ... N5: =SUMIFS($U$32:$U$499,$P$32:$P$499,N$3,$Q$32:$Q$499,"Customer Success")*Hiring_Pace -> 28
B6: Marketing Headcount | C6: =SUMIFS($U$32:$U$499,$P$32:$P$499,C$3,$Q$32:$Q$499,"Marketing")*Hiring_Pace -> 19 | D6: =SUMIFS($U$32:$U$499,$P$32:$P$499,D$3,$Q$32:$Q$499,"Marketing")*Hiring_Pace -> 19 | E6: =SUMIFS($U$32:$U$499,$P$32:$P$499,E$3,$Q$32:$Q$499,"Marketing")*Hiring_Pace -> 19 | F6: =SUMIFS($U$32:$U$499,$P$32:$P$499,F$3,$Q$32:$Q$499,"Marketing")*Hiring_Pace -> 19 | G6: =SUMIFS($U$32:$U$499,$P$32:$P$499,G$3,$Q$32:$Q$499,"Marketing")*Hiring_Pace -> 19 | H6: =SUMIFS($U$32:$U$499,$P$32:$P$499,H$3,$Q$32:$Q$499,"Marketing")*Hiring_Pace -> 19 | I6: =SUMIFS($U$32:$U$499,$P$32:$P$499,I$3,$Q$32:$Q$499,"Marketing")*Hiring_Pace -> 19 | J6: =SUMIFS($U$32:$U$499,$P$32:$P$499,J$3,$Q$32:$Q$499,"Marketing")*Hiring_Pace -> 17 | ... N6: =SUMIFS($U$32:$U$499,$P$32:$P$499,N$3,$Q$32:$Q$499,"Marketing")*Hiring_Pace -> 15
B7: Product & Engineering Headcount | C7: =SUMIFS($U$32:$U$499,$P$32:$P$499,C$3,$Q$32:$Q$499,"Product & Engineering")*Hiring_Pace -> 83 | D7: =SUMIFS($U$32:$U$499,$P$32:$P$499,D$3,$Q$32:$Q$499,"Product & Engineering")*Hiring_Pace -> 83 | E7: =SUMIFS($U$32:$U$499,$P$32:$P$499,E$3,$Q$32:$Q$499,"Product & Engineering")*Hiring_Pace -> 83 | F7: =SUMIFS($U$32:$U$499,$P$32:$P$499,F$3,$Q$32:$Q$499,"Product & Engineering")*Hiring_Pace -> 84 | G7: =SUMIFS($U$32:$U$499,$P$32:$P$499,G$3,$Q$32:$Q$499,"Product & Engineering")*Hiring_Pace -> 84 | H7: =SUMIFS($U$32:$U$499,$P$32:$P$499,H$3,$Q$32:$Q$499,"Product & Engineering")*Hiring_Pace -> 85 | I7: =SUMIFS($U$32:$U$499,$P$32:$P$499,I$3,$Q$32:$Q$499,"Product & Engineering")*Hiring_Pace -> 85 | J7: =SUMIFS($U$32:$U$499,$P$32:$P$499,J$3,$Q$32:$Q$499,"Product & Engineering")*Hiring_Pace -> 82 | ... N7: =SUMIFS($U$32:$U$499,$P$32:$P$499,N$3,$Q$32:$Q$499,"Product & Engineering")*Hiring_Pace -> 80
B8: G&A Headcount | C8: =SUMIFS($U$32:$U$499,$P$32:$P$499,C$3,$Q$32:$Q$499,"G&A")*Hiring_Pace -> 24 | D8: =SUMIFS($U$32:$U$499,$P$32:$P$499,D$3,$Q$32:$Q$499,"G&A")*Hiring_Pace -> 24 | E8: =SUMIFS($U$32:$U$499,$P$32:$P$499,E$3,$Q$32:$Q$499,"G&A")*Hiring_Pace -> 24 | F8: =SUMIFS($U$32:$U$499,$P$32:$P$499,F$3,$Q$32:$Q$499,"G&A")*Hiring_Pace -> 24 | G8: =SUMIFS($U$32:$U$499,$P$32:$P$499,G$3,$Q$32:$Q$499,"G&A")*Hiring_Pace -> 24 | H8: =SUMIFS($U$32:$U$499,$P$32:$P$499,H$3,$Q$32:$Q$499,"G&A")*Hiring_Pace -> 24 | I8: =SUMIFS($U$32:$U$499,$P$32:$P$499,I$3,$Q$32:$Q$499,"G&A")*Hiring_Pace -> 24 | J8: =SUMIFS($U$32:$U$499,$P$32:$P$499,J$3,$Q$32:$Q$499,"G&A")*Hiring_Pace -> 22 | ... N8: =SUMIFS($U$32:$U$499,$P$32:$P$499,N$3,$Q$32:$Q$499,"G&A")*Hiring_Pace -> 20
B9: Total Headcount | C9: =SUM(C4:C8) -> 229 | D9: =SUM(D4:D8) -> 229 | E9: =SUM(E4:E8) -> 229 | F9: =SUM(F4:F8) -> 231 | G9: =SUM(G4:G8) -> 232 | H9: =SUM(H4:H8) -> 233 | I9: =SUM(I4:I8) -> 235 | J9: =SUM(J4:J8) -> 223 | ... N9: =SUM(N4:N8) -> 211
B11: Personnel Opex
B12: Sales Personnel Cost | C12: =SUMIFS($V$32:$V$499,$P$32:$P$499,C$3,$Q$32:$Q$499,"Sales")*Hiring_Pace -> 966666.67 | D12: =SUMIFS($V$32:$V$499,$P$32:$P$499,D$3,$Q$32:$Q$499,"Sales")*Hiring_Pace -> 966666.67 | E12: =SUMIFS($V$32:$V$499,$P$32:$P$499,E$3,$Q$32:$Q$499,"Sales")*Hiring_Pace -> 966666.67 | F12: =SUMIFS($V$32:$V$499,$P$32:$P$499,F$3,$Q$32:$Q$499,"Sales")*Hiring_Pace -> 982083.33 | G12: =SUMIFS($V$32:$V$499,$P$32:$P$499,G$3,$Q$32:$Q$499,"Sales")*Hiring_Pace -> 990833.33 | H12: =SUMIFS($V$32:$V$499,$P$32:$P$499,H$3,$Q$32:$Q$499,"Sales")*Hiring_Pace -> 990833.33 | I12: =SUMIFS($V$32:$V$499,$P$32:$P$499,I$3,$Q$32:$Q$499,"Sales")*Hiring_Pace -> 1006250 | J12: =SUMIFS($V$32:$V$499,$P$32:$P$499,J$3,$Q$32:$Q$499,"Sales")*Hiring_Pace -> 962083.33 | ... N12: =SUMIFS($V$32:$V$499,$P$32:$P$499,N$3,$Q$32:$Q$499,"Sales")*Hiring_Pace -> 917916.67
B13: Customer Success Personnel Cost | C13: =SUMIFS($V$32:$V$499,$P$32:$P$499,C$3,$Q$32:$Q$499,"Customer Success")*Hiring_Pace -> 322500 | D13: =SUMIFS($V$32:$V$499,$P$32:$P$499,D$3,$Q$32:$Q$499,"Customer Success")*Hiring_Pace -> 322500 | E13: =SUMIFS($V$32:$V$499,$P$32:$P$499,E$3,$Q$32:$Q$499,"Customer Success")*Hiring_Pace -> 322500 | F13: =SUMIFS($V$32:$V$499,$P$32:$P$499,F$3,$Q$32:$Q$499,"Customer Success")*Hiring_Pace -> 322500 | G13: =SUMIFS($V$32:$V$499,$P$32:$P$499,G$3,$Q$32:$Q$499,"Customer Success")*Hiring_Pace -> 322500 | H13: =SUMIFS($V$32:$V$499,$P$32:$P$499,H$3,$Q$32:$Q$499,"Customer Success")*Hiring_Pace -> 322500 | I13: =SUMIFS($V$32:$V$499,$P$32:$P$499,I$3,$Q$32:$Q$499,"Customer Success")*Hiring_Pace -> 332916.66 | J13: =SUMIFS($V$32:$V$499,$P$32:$P$499,J$3,$Q$32:$Q$499,"Customer Success")*Hiring_Pace -> 313166.67 | ... N13: =SUMIFS($V$32:$V$499,$P$32:$P$499,N$3,$Q$32:$Q$499,"Customer Success")*Hiring_Pace -> 283000
B14: Marketing Personnel Cost | C14: =SUMIFS($V$32:$V$499,$P$32:$P$499,C$3,$Q$32:$Q$499,"Marketing")*Hiring_Pace -> 220916.67 | D14: =SUMIFS($V$32:$V$499,$P$32:$P$499,D$3,$Q$32:$Q$499,"Marketing")*Hiring_Pace -> 220916.67 | E14: =SUMIFS($V$32:$V$499,$P$32:$P$499,E$3,$Q$32:$Q$499,"Marketing")*Hiring_Pace -> 220916.67 | F14: =SUMIFS($V$32:$V$499,$P$32:$P$499,F$3,$Q$32:$Q$499,"Marketing")*Hiring_Pace -> 220916.67 | G14: =SUMIFS($V$32:$V$499,$P$32:$P$499,G$3,$Q$32:$Q$499,"Marketing")*Hiring_Pace -> 220916.67 | H14: =SUMIFS($V$32:$V$499,$P$32:$P$499,H$3,$Q$32:$Q$499,"Marketing")*Hiring_Pace -> 220916.67 | I14: =SUMIFS($V$32:$V$499,$P$32:$P$499,I$3,$Q$32:$Q$499,"Marketing")*Hiring_Pace -> 220916.67 | J14: =SUMIFS($V$32:$V$499,$P$32:$P$499,J$3,$Q$32:$Q$499,"Marketing")*Hiring_Pace -> 197833.33 | ... N14: =SUMIFS($V$32:$V$499,$P$32:$P$499,N$3,$Q$32:$Q$499,"Marketing")*Hiring_Pace -> 174750
B15: Product & Engineering Personnel Cost | C15: =SUMIFS($V$32:$V$499,$P$32:$P$499,C$3,$Q$32:$Q$499,"Product & Engineering")*Hiring_Pace -> 1177916.7 | D15: =SUMIFS($V$32:$V$499,$P$32:$P$499,D$3,$Q$32:$Q$499,"Product & Engineering")*Hiring_Pace -> 1177916.7 | E15: =SUMIFS($V$32:$V$499,$P$32:$P$499,E$3,$Q$32:$Q$499,"Product & Engineering")*Hiring_Pace -> 1177916.7 | F15: =SUMIFS($V$32:$V$499,$P$32:$P$499,F$3,$Q$32:$Q$499,"Product & Engineering")*Hiring_Pace -> 1192500 | G15: =SUMIFS($V$32:$V$499,$P$32:$P$499,G$3,$Q$32:$Q$499,"Product & Engineering")*Hiring_Pace -> 1192500 | H15: =SUMIFS($V$32:$V$499,$P$32:$P$499,H$3,$Q$32:$Q$499,"Product & Engineering")*Hiring_Pace -> 1207083.3 | I15: =SUMIFS($V$32:$V$499,$P$32:$P$499,I$3,$Q$32:$Q$499,"Product & Engineering")*Hiring_Pace -> 1207083.3 | J15: =SUMIFS($V$32:$V$499,$P$32:$P$499,J$3,$Q$32:$Q$499,"Product & Engineering")*Hiring_Pace -> 1166666.7 | ... N15: =SUMIFS($V$32:$V$499,$P$32:$P$499,N$3,$Q$32:$Q$499,"Product & Engineering")*Hiring_Pace -> 1140833.3
B16: G&A Personnel Cost | C16: =SUMIFS($V$32:$V$499,$P$32:$P$499,C$3,$Q$32:$Q$499,"G&A")*Hiring_Pace -> 282916.66 | D16: =SUMIFS($V$32:$V$499,$P$32:$P$499,D$3,$Q$32:$Q$499,"G&A")*Hiring_Pace -> 282916.66 | E16: =SUMIFS($V$32:$V$499,$P$32:$P$499,E$3,$Q$32:$Q$499,"G&A")*Hiring_Pace -> 282916.66 | F16: =SUMIFS($V$32:$V$499,$P$32:$P$499,F$3,$Q$32:$Q$499,"G&A")*Hiring_Pace -> 282916.66 | G16: =SUMIFS($V$32:$V$499,$P$32:$P$499,G$3,$Q$32:$Q$499,"G&A")*Hiring_Pace -> 282916.66 | H16: =SUMIFS($V$32:$V$499,$P$32:$P$499,H$3,$Q$32:$Q$499,"G&A")*Hiring_Pace -> 282916.66 | I16: =SUMIFS($V$32:$V$499,$P$32:$P$499,I$3,$Q$32:$Q$499,"G&A")*Hiring_Pace -> 282916.66 | J16: =SUMIFS($V$32:$V$499,$P$32:$P$499,J$3,$Q$32:$Q$499,"G&A")*Hiring_Pace -> 258583.33 | ... N16: =SUMIFS($V$32:$V$499,$P$32:$P$499,N$3,$Q$32:$Q$499,"G&A")*Hiring_Pace -> 234250
B17: Total Personnel Cost | C17: =SUM(C12:C16) -> 2970916.7 | D17: =SUM(D12:D16) -> 2970916.7 | E17: =SUM(E12:E16) -> 2970916.7 | F17: =SUM(F12:F16) -> 3000916.7 | G17: =SUM(G12:G16) -> 3009666.7 | H17: =SUM(H12:H16) -> 3024250 | I17: =SUM(I12:I16) -> 3050083.3 | J17: =SUM(J12:J16) -> 2898333.3 | ... N17: =SUM(N12:N16) -> 2750750
B19: Non-Personnel Opex
B20: Sales Non-Personnel | C20: =260000*(1+Merit_Increase)^(MONTH(C$3)/12) -> 260851.17 | D20: =260000*(1+Merit_Increase)^(MONTH(D$3)/12) -> 261705.13 | E20: =260000*(1+Merit_Increase)^(MONTH(E$3)/12) -> 262561.89 | F20: =260000*(1+Merit_Increase)^(MONTH(F$3)/12) -> 263421.44 | G20: =260000*(1+Merit_Increase)^(MONTH(G$3)/12) -> 264283.82 | H20: =260000*(1+Merit_Increase)^(MONTH(H$3)/12) -> 265149.01 | I20: =260000*(1+Merit_Increase)^(MONTH(I$3)/12) -> 266017.04 | J20: =260000*(1+Merit_Increase)^(MONTH(J$3)/12) -> 266887.91 | ... N20: =260000*(1+Merit_Increase)^(MONTH(N$3)/12) -> 270400
B21: Customer Success Non-Personnel | C21: =90000*(1+Merit_Increase)^(MONTH(C$3)/12) -> 90294.637 | D21: =90000*(1+Merit_Increase)^(MONTH(D$3)/12) -> 90590.238 | E21: =90000*(1+Merit_Increase)^(MONTH(E$3)/12) -> 90886.807 | F21: =90000*(1+Merit_Increase)^(MONTH(F$3)/12) -> 91184.346 | G21: =90000*(1+Merit_Increase)^(MONTH(G$3)/12) -> 91482.86 | H21: =90000*(1+Merit_Increase)^(MONTH(H$3)/12) -> 91782.351 | I21: =90000*(1+Merit_Increase)^(MONTH(I$3)/12) -> 92082.823 | J21: =90000*(1+Merit_Increase)^(MONTH(J$3)/12) -> 92384.278 | ... N21: =90000*(1+Merit_Increase)^(MONTH(N$3)/12) -> 93600
B22: Marketing Non-Personnel | C22: =520000*(1+Merit_Increase)^(MONTH(C$3)/12) -> 521702.34 | D22: =520000*(1+Merit_Increase)^(MONTH(D$3)/12) -> 523410.26 | E22: =520000*(1+Merit_Increase)^(MONTH(E$3)/12) -> 525123.77 | F22: =520000*(1+Merit_Increase)^(MONTH(F$3)/12) -> 526842.89 | G22: =520000*(1+Merit_Increase)^(MONTH(G$3)/12) -> 528567.64 | H22: =520000*(1+Merit_Increase)^(MONTH(H$3)/12) -> 530298.03 | I22: =520000*(1+Merit_Increase)^(MONTH(I$3)/12) -> 532034.09 | J22: =520000*(1+Merit_Increase)^(MONTH(J$3)/12) -> 533775.83 | ... N22: =520000*(1+Merit_Increase)^(MONTH(N$3)/12) -> 540800
B23: Product & Engineering Non-Personnel | C23: =280000*(1+Merit_Increase)^(MONTH(C$3)/12) -> 280916.65 | D23: =280000*(1+Merit_Increase)^(MONTH(D$3)/12) -> 281836.3 | E23: =280000*(1+Merit_Increase)^(MONTH(E$3)/12) -> 282758.95 | F23: =280000*(1+Merit_Increase)^(MONTH(F$3)/12) -> 283684.63 | G23: =280000*(1+Merit_Increase)^(MONTH(G$3)/12) -> 284613.34 | H23: =280000*(1+Merit_Increase)^(MONTH(H$3)/12) -> 285545.09 | I23: =280000*(1+Merit_Increase)^(MONTH(I$3)/12) -> 286479.89 | J23: =280000*(1+Merit_Increase)^(MONTH(J$3)/12) -> 287417.75 | ... N23: =280000*(1+Merit_Increase)^(MONTH(N$3)/12) -> 291200
B24: G&A Non-Personnel | C24: =210000*(1+Merit_Increase)^(MONTH(C$3)/12) -> 210687.49 | D24: =210000*(1+Merit_Increase)^(MONTH(D$3)/12) -> 211377.22 | E24: =210000*(1+Merit_Increase)^(MONTH(E$3)/12) -> 212069.22 | F24: =210000*(1+Merit_Increase)^(MONTH(F$3)/12) -> 212763.47 | G24: =210000*(1+Merit_Increase)^(MONTH(G$3)/12) -> 213460.01 | H24: =210000*(1+Merit_Increase)^(MONTH(H$3)/12) -> 214158.82 | I24: =210000*(1+Merit_Increase)^(MONTH(I$3)/12) -> 214859.92 | J24: =210000*(1+Merit_Increase)^(MONTH(J$3)/12) -> 215563.32 | ... N24: =210000*(1+Merit_Increase)^(MONTH(N$3)/12) -> 218400
B25: Total Non-Personnel | C25: =SUM(C20:C24) -> 1364452.3 | D25: =SUM(D20:D24) -> 1368919.1 | E25: =SUM(E20:E24) -> 1373400.6 | F25: =SUM(F20:F24) -> 1377896.8 | G25: =SUM(G20:G24) -> 1382407.7 | H25: =SUM(H20:H24) -> 1386933.3 | I25: =SUM(I20:I24) -> 1391473.8 | J25: =SUM(J20:J24) -> 1396029.1 | ... N25: =SUM(N20:N24) -> 1414400
B27: Total Opex | C27: =C17+C25 -> 4335369 | D27: =D17+D25 -> 4339835.8 | E27: =E17+E25 -> 4344317.3 | F27: =F17+F25 -> 4378813.4 | G27: =G17+G25 -> 4392074.3 | H27: =H17+H25 -> 4411183.3 | I27: =I17+I25 -> 4441557.1 | J27: =J17+J25 -> 4294362.4 | ... N27: =N17+N25 -> 4165150
P31: month | Q31: department | R31: role | S31: start_date | T31: fully_loaded_annual_cost | U31: headcount | V31: monthly_cost
P32: 45292 | Q32: Sales | R32: Account Executive | S32: 2024-01-01 | T32: 185000 | U32: 32 | V32: 493333.33
P33: 45292 | Q33: Sales | R33: Sales Development Rep | S33: 2024-01-01 | T33: 105000 | U33: 18 | V33: 157500
P34: 45292 | Q34: Sales | R34: Sales Leadership | S34: 2024-01-01 | T34: 240000 | U34: 5 | V34: 100000
P35: 45292 | Q35: Customer Success | R35: Customer Success Manager | S35: 2024-01-01 | T35: 125000 | U35: 18 | V35: 187500
P36: 45292 | Q36: Customer Success | R36: Implementation | S36: 2024-01-01 | T36: 112000 | U36: 8 | V36: 74666.67
P37: 45292 | Q37: Marketing | R37: Demand Generation | S37: 2024-01-01 | T37: 145000 | U37: 9 | V37: 108750
P38: 45292 | Q38: Marketing | R38: Content & Brand | S38: 2024-01-01 | T38: 132000 | U38: 6 | V38: 66000
P39: 45292 | Q39: Product & Engineering | R39: Software Engineer | S39: 2024-01-01 | T39: 175000 | U39: 52 | V39: 758333.33
P40: 45292 | Q40: Product & Engineering | R40: Product Manager | S40: 2024-01-01 | T40: 165000 | U40: 10 | V40: 137500
P41: 45292 | Q41: Product & Engineering | R41: Design & Research | S41: 2024-01-01 | T41: 145000 | U41: 7 | V41: 84583.33
P42: 45292 | Q42: G&A | R42: Finance & Accounting | S42: 2024-01-01 | T42: 142000 | U42: 8 | V42: 94666.67
P43: 45292 | Q43: G&A | R43: People & Legal | S43: 2024-01-01 | T43: 150000 | U43: 7 | V43: 87500
... P499: 46357 | Q499: G&A | R499: IT & Facilities | S499: 2024-01-01 | T499: 125000 | U499: 5 | V499: 52083.33

Sheet Income Statement
A1: Income Statement | linked monthly operating forecast
C3: 46023 | D3: 46054 | E3: 46082 | F3: 46113 | G3: 46143 | H3: 46174 | I3: 46204 | J3: 46235 | K3: 46266 | L3: 46296 | M3: 46327 | N3: 46357
B4: Revenue | C4: ='Revenue Forecast'!C33 -> 4058888.2 | D4: ='Revenue Forecast'!D33 -> 4106582.7 | E4: ='Revenue Forecast'!E33 -> 4172873.3 | F4: ='Revenue Forecast'!F33 -> 4235179.2 | G4: ='Revenue Forecast'!G33 -> 4266640.3 | H4: ='Revenue Forecast'!H33 -> 4306837.7 | I4: ='Revenue Forecast'!I33 -> 4376786.8 | J4: ='Revenue Forecast'!J33 -> 4431993.6 | ... N4: ='Revenue Forecast'!N33 -> 4770108.8
B5: Cost of Revenue | C5: =-C4*(1-Gross_Margin) -> -791483.21 | D5: =-D4*(1-Gross_Margin) -> -800783.62 | E5: =-E4*(1-Gross_Margin) -> -813710.3 | F5: =-F4*(1-Gross_Margin) -> -825859.94 | G5: =-G4*(1-Gross_Margin) -> -831994.86 | H5: =-H4*(1-Gross_Margin) -> -839833.35 | I5: =-I4*(1-Gross_Margin) -> -853473.42 | J5: =-J4*(1-Gross_Margin) -> -864238.75 | ... N5: =-N4*(1-Gross_Margin) -> -930171.22
B6: Gross Profit | C6: =SUM(C4:C5) -> 3267405 | D6: =SUM(D4:D5) -> 3305799 | E6: =SUM(E4:E5) -> 3359163 | F6: =SUM(F4:F5) -> 3409319.3 | G6: =SUM(G4:G5) -> 3434645.5 | H6: =SUM(H4:H5) -> 3467004.3 | I6: =SUM(I4:I5) -> 3523313.3 | J6: =SUM(J4:J5) -> 3567754.8 | ... N6: =SUM(N4:N5) -> 3839937.6
B7: Gross Margin | C7: =IFERROR(C6/C4,0) -> 0.805 | D7: =IFERROR(D6/D4,0) -> 0.805 | E7: =IFERROR(E6/E4,0) -> 0.805 | F7: =IFERROR(F6/F4,0) -> 0.805 | G7: =IFERROR(G6/G4,0) -> 0.805 | H7: =IFERROR(H6/H4,0) -> 0.805 | I7: =IFERROR(I6/I4,0) -> 0.805 | J7: =IFERROR(J6/J4,0) -> 0.805 | ... N7: =IFERROR(N6/N4,0) -> 0.805
B9: Sales & Marketing | C9: =-SUM('Headcount & Opex Plan'!C12,'Headcount & Opex Plan'!C14,'Headcount & Opex Plan'!C20,'Headcount & Opex Plan'!C22) -> -1970136.9 | D9: =-SUM('Headcount & Opex Plan'!D12,'Headcount & Opex Plan'!D14,'Headcount & Opex Plan'!D20,'Headcount & Opex Plan'!D22) -> -1972698.7 | E9: =-SUM('Headcount & Opex Plan'!E12,'Headcount & Opex Plan'!E14,'Headcount & Opex Plan'!E20,'Headcount & Opex Plan'!E22) -> -1975269 | F9: =-SUM('Headcount & Opex Plan'!F12,'Headcount & Opex Plan'!F14,'Headcount & Opex Plan'!F20,'Headcount & Opex Plan'!F22) -> -1993264.3 | G9: =-SUM('Headcount & Opex Plan'!G12,'Headcount & Opex Plan'!G14,'Headcount & Opex Plan'!G20,'Headcount & Opex Plan'!G22) -> -2004601.5 | H9: =-SUM('Headcount & Opex Plan'!H12,'Headcount & Opex Plan'!H14,'Headcount & Opex Plan'!H20,'Headcount & Opex Plan'!H22) -> -2007197 | I9: =-SUM('Headcount & Opex Plan'!I12,'Headcount & Opex Plan'!I14,'Headcount & Opex Plan'!I20,'Headcount & Opex Plan'!I22) -> -2025217.8 | J9: =-SUM('Headcount & Opex Plan'!J12,'Headcount & Opex Plan'!J14,'Headcount & Opex Plan'!J20,'Headcount & Opex Plan'!J22) -> -1960580.4 | ... N9: =-SUM('Headcount & Opex Plan'!N12,'Headcount & Opex Plan'!N14,'Headcount & Opex Plan'!N20,'Headcount & Opex Plan'!N22) -> -1903866.7
B10: Customer Success | C10: =-SUM('Headcount & Opex Plan'!C13,'Headcount & Opex Plan'!C21) -> -412794.64 | D10: =-SUM('Headcount & Opex Plan'!D13,'Headcount & Opex Plan'!D21) -> -413090.24 | E10: =-SUM('Headcount & Opex Plan'!E13,'Headcount & Opex Plan'!E21) -> -413386.81 | F10: =-SUM('Headcount & Opex Plan'!F13,'Headcount & Opex Plan'!F21) -> -413684.35 | G10: =-SUM('Headcount & Opex Plan'!G13,'Headcount & Opex Plan'!G21) -> -413982.86 | H10: =-SUM('Headcount & Opex Plan'!H13,'Headcount & Opex Plan'!H21) -> -414282.35 | I10: =-SUM('Headcount & Opex Plan'!I13,'Headcount & Opex Plan'!I21) -> -424999.48 | J10: =-SUM('Headcount & Opex Plan'!J13,'Headcount & Opex Plan'!J21) -> -405550.95 | ... N10: =-SUM('Headcount & Opex Plan'!N13,'Headcount & Opex Plan'!N21) -> -376600
B11: Product & Engineering | C11: =-SUM('Headcount & Opex Plan'!C15,'Headcount & Opex Plan'!C23) -> -1458833.3 | D11: =-SUM('Headcount & Opex Plan'!D15,'Headcount & Opex Plan'!D23) -> -1459753 | E11: =-SUM('Headcount & Opex Plan'!E15,'Headcount & Opex Plan'!E23) -> -1460675.6 | F11: =-SUM('Headcount & Opex Plan'!F15,'Headcount & Opex Plan'!F23) -> -1476184.6 | G11: =-SUM('Headcount & Opex Plan'!G15,'Headcount & Opex Plan'!G23) -> -1477113.3 | H11: =-SUM('Headcount & Opex Plan'!H15,'Headcount & Opex Plan'!H23) -> -1492628.4 | I11: =-SUM('Headcount & Opex Plan'!I15,'Headcount & Opex Plan'!I23) -> -1493563.2 | J11: =-SUM('Headcount & Opex Plan'!J15,'Headcount & Opex Plan'!J23) -> -1454084.4 | ... N11: =-SUM('Headcount & Opex Plan'!N15,'Headcount & Opex Plan'!N23) -> -1432033.3
B12: G&A | C12: =-SUM('Headcount & Opex Plan'!C16,'Headcount & Opex Plan'!C24) -> -493604.15 | D12: =-SUM('Headcount & Opex Plan'!D16,'Headcount & Opex Plan'!D24) -> -494293.88 | E12: =-SUM('Headcount & Opex Plan'!E16,'Headcount & Opex Plan'!E24) -> -494985.88 | F12: =-SUM('Headcount & Opex Plan'!F16,'Headcount & Opex Plan'!F24) -> -495680.13 | G12: =-SUM('Headcount & Opex Plan'!G16,'Headcount & Opex Plan'!G24) -> -496376.67 | H12: =-SUM('Headcount & Opex Plan'!H16,'Headcount & Opex Plan'!H24) -> -497075.48 | I12: =-SUM('Headcount & Opex Plan'!I16,'Headcount & Opex Plan'!I24) -> -497776.58 | J12: =-SUM('Headcount & Opex Plan'!J16,'Headcount & Opex Plan'!J24) -> -474146.65 | ... N12: =-SUM('Headcount & Opex Plan'!N16,'Headcount & Opex Plan'!N24) -> -452650
B13: Total Opex | C13: =SUM(C9:C12) -> -4335369 | D13: =SUM(D9:D12) -> -4339835.8 | E13: =SUM(E9:E12) -> -4344317.3 | F13: =SUM(F9:F12) -> -4378813.4 | G13: =SUM(G9:G12) -> -4392074.3 | H13: =SUM(H9:H12) -> -4411183.3 | I13: =SUM(I9:I12) -> -4441557.1 | J13: =SUM(J9:J12) -> -4294362.4 | ... N13: =SUM(N9:N12) -> -4165150
B14: EBITDA | C14: =C6+C13 -> -1067963.9 | D14: =D6+D13 -> -1034036.8 | E14: =E6+E13 -> -985154.26 | F14: =F6+F13 -> -969494.19 | G14: =G6+G13 -> -957428.86 | H14: =H6+H13 -> -944178.97 | I14: =I6+I13 -> -918243.74 | J14: =J6+J13 -> -726607.6 | ... N14: =N6+N13 -> -325212.39
B15: EBITDA Margin | C15: =IFERROR(C14/C4,0) -> -0.26311735 | D15: =IFERROR(D14/D4,0) -> -0.25179982 | E15: =IFERROR(E14/E4,0) -> -0.23608535 | F15: =IFERROR(F14/F4,0) -> -0.22891456 | G15: =IFERROR(G14/G4,0) -> -0.22439877 | H15: =IFERROR(H14/H4,0) -> -0.2192279 | I15: =IFERROR(I14/I4,0) -> -0.2097986 | J15: =IFERROR(J14/J4,0) -> -0.163946 | ... N15: =IFERROR(N14/N4,0) -> -0.068177143
B17: Depreciation & Amortization | C17: =-'Cash Flow Statement'!C8 -> -2224393.6 | D17: =-'Cash Flow Statement'!D8 -> -4764.6525 | E17: =-'Cash Flow Statement'!E8 -> -4780.2507 | F17: =-'Cash Flow Statement'!F8 -> -36795.889 | G17: =-'Cash Flow Statement'!G8 -> -14144.934 | H17: =-'Cash Flow Statement'!H8 -> -20382.904 | I17: =-'Cash Flow Statement'!I8 -> -32398.708 | J17: =-'Cash Flow Statement'!J8 -> 157007.64 | ... N17: =-'Cash Flow Statement'!N8 -> 47521.484
B18: EBIT | C18: =SUM(C14,C17) -> -3292357.5 | D18: =SUM(D14,D17) -> -1038801.4 | E18: =SUM(E14,E17) -> -989934.52 | F18: =SUM(F14,F17) -> -1006290.1 | G18: =SUM(G14,G17) -> -971573.79 | H18: =SUM(H14,H17) -> -964561.88 | I18: =SUM(I14,I17) -> -950642.45 | J18: =SUM(J14,J17) -> -569599.95 | ... N18: =SUM(N14,N17) -> -277690.91
B19: Interest Income | C19: =Opening_Cash*Interest_Rate/12 -> 67500 | D19: ='Balance Sheet'!C5*Interest_Rate/12 -> 61810.069 | E19: ='Balance Sheet'!D5*Interest_Rate/12 -> 57690.705 | F19: ='Balance Sheet'!E5*Interest_Rate/12 -> 53639.101 | G19: ='Balance Sheet'!F5*Interest_Rate/12 -> 49631.42 | H19: ='Balance Sheet'!G5*Interest_Rate/12 -> 45790.655 | I19: ='Balance Sheet'!H5*Interest_Rate/12 -> 41931.807 | J19: ='Balance Sheet'!I5*Interest_Rate/12 -> 37999.611 | K19: ='Balance Sheet'!J5*Interest_Rate/12 -> 34859.664 | ... N19: ='Balance Sheet'!M5*Interest_Rate/12 -> 27055.01
B20: Interest Expense | C20: =-Opening_Debt*6%/12 -> -25000 | D20: =-Opening_Debt*6%/12 -> -25000 | E20: =-Opening_Debt*6%/12 -> -25000 | F20: =-Opening_Debt*6%/12 -> -25000 | G20: =-Opening_Debt*6%/12 -> -25000 | H20: =-Opening_Debt*6%/12 -> -25000 | I20: =-Opening_Debt*6%/12 -> -25000 | J20: =-Opening_Debt*6%/12 -> -25000 | ... N20: =-Opening_Debt*6%/12 -> -25000
B21: Pre-Tax Income | C21: =SUM(C18:C20) -> -3249857.5 | D21: =SUM(D18:D20) -> -1001991.4 | E21: =SUM(E18:E20) -> -957243.81 | F21: =SUM(F18:F20) -> -977650.98 | G21: =SUM(G18:G20) -> -946942.37 | H21: =SUM(H18:H20) -> -943771.22 | I21: =SUM(I18:I20) -> -933710.64 | J21: =SUM(J18:J20) -> -556600.34 | ... N21: =SUM(N18:N20) -> -275635.9
B22: Taxes | C22: =-MAX(0,C21*Tax_Rate) -> 0 | D22: =-MAX(0,D21*Tax_Rate) -> 0 | E22: =-MAX(0,E21*Tax_Rate) -> 0 | F22: =-MAX(0,F21*Tax_Rate) -> 0 | G22: =-MAX(0,G21*Tax_Rate) -> 0 | H22: =-MAX(0,H21*Tax_Rate) -> 0 | I22: =-MAX(0,I21*Tax_Rate) -> 0 | J22: =-MAX(0,J21*Tax_Rate) -> 0 | ... N22: =-MAX(0,N21*Tax_Rate) -> 0
B23: Net Income | C23: =SUM(C21:C22) -> -3249857.5 | D23: =SUM(D21:D22) -> -1001991.4 | E23: =SUM(E21:E22) -> -957243.81 | F23: =SUM(F21:F22) -> -977650.98 | G23: =SUM(G21:G22) -> -946942.37 | H23: =SUM(H21:H22) -> -943771.22 | I23: =SUM(I21:I22) -> -933710.64 | J23: =SUM(J21:J22) -> -556600.34 | ... N23: =SUM(N21:N22) -> -275635.9

Sheet Balance Sheet
A1: Balance Sheet | cash linked from Cash Flow, balance check included
C3: 46023 | D3: 46054 | E3: 46082 | F3: 46113 | G3: 46143 | H3: 46174 | I3: 46204 | J3: 46235 | K3: 46266 | L3: 46296 | M3: 46327 | N3: 46357
B5: Cash | C5: ='Cash Flow Statement'!C17 -> 16482685 | D5: ='Cash Flow Statement'!D17 -> 15384188 | E5: ='Cash Flow Statement'!E17 -> 14303760 | F5: ='Cash Flow Statement'!F17 -> 13235045 | G5: ='Cash Flow Statement'!G17 -> 12210841 | H5: ='Cash Flow Statement'!H17 -> 11181815 | I5: ='Cash Flow Statement'!I17 -> 10133230 | J5: ='Cash Flow Statement'!J17 -> 9295910.3 | ... N5: ='Cash Flow Statement'!N17 -> 6673852.6
B6: Accounts Receivable | C6: ='Income Statement'!C4*DSO/30 -> 6494221.2 | D6: ='Income Statement'!D4*DSO/30 -> 6570532.3 | E6: ='Income Statement'!E4*DSO/30 -> 6676597.3 | F6: ='Income Statement'!F4*DSO/30 -> 6776286.7 | G6: ='Income Statement'!G4*DSO/30 -> 6826624.5 | H6: ='Income Statement'!H4*DSO/30 -> 6890940.3 | I6: ='Income Statement'!I4*DSO/30 -> 7002858.8 | J6: ='Income Statement'!J4*DSO/30 -> 7091189.7 | ... N6: ='Income Statement'!N4*DSO/30 -> 7632174.1
B7: Prepaids & Other Current Assets | C7: ='Income Statement'!C13*-5% -> 216768.45 | D7: ='Income Statement'!D13*-5% -> 216991.79 | E7: ='Income Statement'!E13*-5% -> 217215.87 | F7: ='Income Statement'!F13*-5% -> 218940.67 | G7: ='Income Statement'!G13*-5% -> 219603.72 | H7: ='Income Statement'!H13*-5% -> 220559.16 | I7: ='Income Statement'!I13*-5% -> 222077.85 | J7: ='Income Statement'!J13*-5% -> 214718.12 | ... N7: ='Income Statement'!N13*-5% -> 208257.5
B8: Property & Equipment, Net | C8: =IF(C$3=DATE(2026,1,1),6000000,B8)+'Cash Flow Statement'!C12+'Cash Flow Statement'!C8*-1 -> 3674134.2 | D8: =IF(D$3=DATE(2026,1,1),6000000,C8)+'Cash Flow Statement'!D12+'Cash Flow Statement'!D8*-1 -> 3566705 | E8: =IF(E$3=DATE(2026,1,1),6000000,D8)+'Cash Flow Statement'!E12+'Cash Flow Statement'!E8*-1 -> 3457602.9 | F8: =IF(F$3=DATE(2026,1,1),6000000,E8)+'Cash Flow Statement'!F12+'Cash Flow Statement'!F8*-1 -> 3314927.6 | G8: =IF(G$3=DATE(2026,1,1),6000000,F8)+'Cash Flow Statement'!G12+'Cash Flow Statement'!G8*-1 -> 3194116.6 | H8: =IF(H$3=DATE(2026,1,1),6000000,G8)+'Cash Flow Statement'!H12+'Cash Flow Statement'!H8*-1 -> 3066062.8 | I8: =IF(I$3=DATE(2026,1,1),6000000,H8)+'Cash Flow Statement'!I12+'Cash Flow Statement'!I8*-1 -> 2924244.4 | J8: =IF(J$3=DATE(2026,1,1),6000000,I8)+'Cash Flow Statement'!J12+'Cash Flow Statement'!J8*-1 -> 2970452.2 | ... N8: =IF(N$3=DATE(2026,1,1),6000000,M8)+'Cash Flow Statement'!N12+'Cash Flow Statement'!N8*-1 -> 2644514.1
B9: Total Assets | C9: =SUM(C5:C8) -> 26867809 | D9: =SUM(D5:D8) -> 25738417 | E9: =SUM(E5:E8) -> 24655176 | F9: =SUM(F5:F8) -> 23545200 | G9: =SUM(G5:G8) -> 22451186 | H9: =SUM(H5:H8) -> 21359377 | I9: =SUM(I5:I8) -> 20282411 | J9: =SUM(J5:J8) -> 19572270 | ... N9: =SUM(N5:N8) -> 17158798
B11: Accounts Payable | C11: =-'Income Statement'!C13*DPO/30 -> 4624393.6 | D11: =-'Income Statement'!D13*DPO/30 -> 4629158.2 | E11: =-'Income Statement'!E13*DPO/30 -> 4633938.5 | F11: =-'Income Statement'!F13*DPO/30 -> 4670734.3 | G11: =-'Income Statement'!G13*DPO/30 -> 4684879.3 | H11: =-'Income Statement'!H13*DPO/30 -> 4705262.2 | I11: =-'Income Statement'!I13*DPO/30 -> 4737660.9 | J11: =-'Income Statement'!J13*DPO/30 -> 4580653.2 | ... N11: =-'Income Statement'!N13*DPO/30 -> 4442826.7
B12: Deferred Revenue | C12: ='Income Statement'!C4*0.35 -> 1420610.9 | D12: ='Income Statement'!D4*0.35 -> 1437303.9 | E12: ='Income Statement'!E4*0.35 -> 1460505.7 | F12: ='Income Statement'!F4*0.35 -> 1482312.7 | G12: ='Income Statement'!G4*0.35 -> 1493324.1 | H12: ='Income Statement'!H4*0.35 -> 1507393.2 | I12: ='Income Statement'!I4*0.35 -> 1531875.4 | J12: ='Income Statement'!J4*0.35 -> 1551197.7 | ... N12: ='Income Statement'!N4*0.35 -> 1669538.1
B13: Debt | C13: =Opening_Debt -> 5000000 | D13: =Opening_Debt -> 5000000 | E13: =Opening_Debt -> 5000000 | F13: =Opening_Debt -> 5000000 | G13: =Opening_Debt -> 5000000 | H13: =Opening_Debt -> 5000000 | I13: =Opening_Debt -> 5000000 | J13: =Opening_Debt -> 5000000 | ... N13: =Opening_Debt -> 5000000
B14: Total Liabilities | C14: =SUM(C11:C13) -> 11045004 | D14: =SUM(D11:D13) -> 11066462 | E14: =SUM(E11:E13) -> 11094444 | F14: =SUM(F11:F13) -> 11153047 | G14: =SUM(G11:G13) -> 11178203 | H14: =SUM(H11:H13) -> 11212655 | I14: =SUM(I11:I13) -> 11269536 | J14: =SUM(J11:J13) -> 11131851 | ... N14: =SUM(N11:N13) -> 11112365
B16: Opening Equity | C16: =C9-C14-C17 -> 19072662 | D16: =D9-D14-D17 -> 18923804 | E16: =E9-E14-E17 -> 18769825 | F16: =F9-F14-F17 -> 18578897 | G16: =G9-G14-G17 -> 18406669 | H16: =H9-H14-H17 -> 18224179 | I16: =I9-I14-I17 -> 18024042 | J16: =J9-J14-J17 -> 18008188 | ... N16: =N9-N14-N17 -> 17407942
B17: Retained Earnings | C17: =IF(C$3=DATE(2026,1,1),0,B17)+'Income Statement'!C23 -> -3249857.5 | D17: =IF(D$3=DATE(2026,1,1),0,C17)+'Income Statement'!D23 -> -4251848.8 | E17: =IF(E$3=DATE(2026,1,1),0,D17)+'Income Statement'!E23 -> -5209092.6 | F17: =IF(F$3=DATE(2026,1,1),0,E17)+'Income Statement'!F23 -> -6186743.6 | G17: =IF(G$3=DATE(2026,1,1),0,F17)+'Income Statement'!G23 -> -7133686 | H17: =IF(H$3=DATE(2026,1,1),0,G17)+'Income Statement'!H23 -> -8077457.2 | I17: =IF(I$3=DATE(2026,1,1),0,H17)+'Income Statement'!I23 -> -9011167.9 | J17: =IF(J$3=DATE(2026,1,1),0,I17)+'Income Statement'!J23 -> -9567768.2 | ... N17: =IF(N$3=DATE(2026,1,1),0,M17)+'Income Statement'!N23 -> -11361509
B18: Total Equity | C18: =SUM(C16:C17) -> 15822805 | D18: =SUM(D16:D17) -> 14671955 | E18: =SUM(E16:E17) -> 13560732 | F18: =SUM(F16:F17) -> 12392153 | G18: =SUM(G16:G17) -> 11272983 | H18: =SUM(H16:H17) -> 10146722 | I18: =SUM(I16:I17) -> 9012874.3 | J18: =SUM(J16:J17) -> 8440419.4 | ... N18: =SUM(N16:N17) -> 6046433.6
B20: Liabilities + Equity | C20: =SUM(C14,C18) -> 26867809 | D20: =SUM(D14,D18) -> 25738417 | E20: =SUM(E14,E18) -> 24655176 | F20: =SUM(F14,F18) -> 23545200 | G20: =SUM(G14,G18) -> 22451186 | H20: =SUM(H14,H18) -> 21359377 | I20: =SUM(I14,I18) -> 20282411 | J20: =SUM(J14,J18) -> 19572270 | ... N20: =SUM(N14,N18) -> 17158798
B22: Balance Check | C22: =C9-C20 -> 0 | D22: =D9-D20 -> 0 | E22: =E9-E20 -> 0 | F22: =F9-F20 -> 0 | G22: =G9-G20 -> 0 | H22: =H9-H20 -> 0 | I22: =I9-I20 -> 0 | J22: =J9-J20 -> 0 | ... N22: =N9-N20 -> 0

Sheet Cash Flow Statement
A1: Cash Flow Statement | indirect method
C3: 46023 | D3: 46054 | E3: 46082 | F3: 46113 | G3: 46143 | H3: 46174 | I3: 46204 | J3: 46235 | K3: 46266 | L3: 46296 | M3: 46327 | N3: 46357
B4: Net Income | C4: ='Income Statement'!C23 -> -3249857.5 | D4: ='Income Statement'!D23 -> -1001991.4 | E4: ='Income Statement'!E23 -> -957243.81 | F4: ='Income Statement'!F23 -> -977650.98 | G4: ='Income Statement'!G23 -> -946942.37 | H4: ='Income Statement'!H23 -> -943771.22 | I4: ='Income Statement'!I23 -> -933710.64 | J4: ='Income Statement'!J23 -> -556600.34 | ... N4: ='Income Statement'!N23 -> -275635.9
B5: Depreciation & Amortization | C5: =IF(C$3=DATE(2026,1,1),6000000/60,'Balance Sheet'!B8/60) -> 100000 | D5: =IF(D$3=DATE(2026,1,1),6000000/60,'Balance Sheet'!C8/60) -> 61235.571 | E5: =IF(E$3=DATE(2026,1,1),6000000/60,'Balance Sheet'!D8/60) -> 59445.084 | F5: =IF(F$3=DATE(2026,1,1),6000000/60,'Balance Sheet'!E8/60) -> 57626.716 | G5: =IF(G$3=DATE(2026,1,1),6000000/60,'Balance Sheet'!F8/60) -> 55248.793 | H5: =IF(H$3=DATE(2026,1,1),6000000/60,'Balance Sheet'!G8/60) -> 53235.277 | I5: =IF(I$3=DATE(2026,1,1),6000000/60,'Balance Sheet'!H8/60) -> 51101.046 | J5: =IF(J$3=DATE(2026,1,1),6000000/60,'Balance Sheet'!I8/60) -> 48737.407 | ... N5: =IF(N$3=DATE(2026,1,1),6000000/60,'Balance Sheet'!M8/60) -> 45270.756
B6: Change in Accounts Receivable | C6: =-('Balance Sheet'!C6-IF(C$3=DATE(2026,1,1),5500000,'Balance Sheet'!B6)) -> -994221.17 | D6: =-('Balance Sheet'!D6-IF(D$3=DATE(2026,1,1),5500000,'Balance Sheet'!C6)) -> -76311.096 | E6: =-('Balance Sheet'!E6-IF(E$3=DATE(2026,1,1),5500000,'Balance Sheet'!D6)) -> -106065.07 | F6: =-('Balance Sheet'!F6-IF(F$3=DATE(2026,1,1),5500000,'Balance Sheet'!E6)) -> -99689.384 | G6: =-('Balance Sheet'!G6-IF(G$3=DATE(2026,1,1),5500000,'Balance Sheet'!F6)) -> -50337.803 | H6: =-('Balance Sheet'!H6-IF(H$3=DATE(2026,1,1),5500000,'Balance Sheet'!G6)) -> -64315.741 | I6: =-('Balance Sheet'!I6-IF(I$3=DATE(2026,1,1),5500000,'Balance Sheet'!H6)) -> -111918.55 | J6: =-('Balance Sheet'!J6-IF(J$3=DATE(2026,1,1),5500000,'Balance Sheet'!I6)) -> -88330.884 | ... N6: =-('Balance Sheet'!N6-IF(N$3=DATE(2026,1,1),5500000,'Balance Sheet'!M6)) -> -186758.4
B7: Change in Prepaids | C7: =-('Balance Sheet'!C7-IF(C$3=DATE(2026,1,1),600000,'Balance Sheet'!B7)) -> 383231.55 | D7: =-('Balance Sheet'!D7-IF(D$3=DATE(2026,1,1),600000,'Balance Sheet'!C7)) -> -223.34309 | E7: =-('Balance Sheet'!E7-IF(E$3=DATE(2026,1,1),600000,'Balance Sheet'!D7)) -> -224.07425 | F7: =-('Balance Sheet'!F7-IF(F$3=DATE(2026,1,1),600000,'Balance Sheet'!E7)) -> -1724.8073 | G7: =-('Balance Sheet'!G7-IF(G$3=DATE(2026,1,1),600000,'Balance Sheet'!F7)) -> -663.04378 | H7: =-('Balance Sheet'!H7-IF(H$3=DATE(2026,1,1),600000,'Balance Sheet'!G7)) -> -955.44865 | I7: =-('Balance Sheet'!I7-IF(I$3=DATE(2026,1,1),600000,'Balance Sheet'!H7)) -> -1518.6894 | J7: =-('Balance Sheet'!J7-IF(J$3=DATE(2026,1,1),600000,'Balance Sheet'!I7)) -> 7359.7333 | ... N7: =-('Balance Sheet'!N7-IF(N$3=DATE(2026,1,1),600000,'Balance Sheet'!M7)) -> 2227.5696
B8: Change in Accounts Payable | C8: ='Balance Sheet'!C11-IF(C$3=DATE(2026,1,1),2400000,'Balance Sheet'!B11) -> 2224393.6 | D8: ='Balance Sheet'!D11-IF(D$3=DATE(2026,1,1),2400000,'Balance Sheet'!C11) -> 4764.6525 | E8: ='Balance Sheet'!E11-IF(E$3=DATE(2026,1,1),2400000,'Balance Sheet'!D11) -> 4780.2507 | F8: ='Balance Sheet'!F11-IF(F$3=DATE(2026,1,1),2400000,'Balance Sheet'!E11) -> 36795.889 | G8: ='Balance Sheet'!G11-IF(G$3=DATE(2026,1,1),2400000,'Balance Sheet'!F11) -> 14144.934 | H8: ='Balance Sheet'!H11-IF(H$3=DATE(2026,1,1),2400000,'Balance Sheet'!G11) -> 20382.904 | I8: ='Balance Sheet'!I11-IF(I$3=DATE(2026,1,1),2400000,'Balance Sheet'!H11) -> 32398.708 | J8: ='Balance Sheet'!J11-IF(J$3=DATE(2026,1,1),2400000,'Balance Sheet'!I11) -> -157007.64 | ... N8: ='Balance Sheet'!N11-IF(N$3=DATE(2026,1,1),2400000,'Balance Sheet'!M11) -> -47521.484
B9: Change in Deferred Revenue | C9: ='Balance Sheet'!C12-IF(C$3=DATE(2026,1,1),1300000,'Balance Sheet'!B12) -> 120610.88 | D9: ='Balance Sheet'!D12-IF(D$3=DATE(2026,1,1),1300000,'Balance Sheet'!C12) -> 16693.052 | E9: ='Balance Sheet'!E12-IF(E$3=DATE(2026,1,1),1300000,'Balance Sheet'!D12) -> 23201.735 | F9: ='Balance Sheet'!F12-IF(F$3=DATE(2026,1,1),1300000,'Balance Sheet'!E12) -> 21807.053 | G9: ='Balance Sheet'!G12-IF(G$3=DATE(2026,1,1),1300000,'Balance Sheet'!F12) -> 11011.394 | H9: ='Balance Sheet'!H12-IF(H$3=DATE(2026,1,1),1300000,'Balance Sheet'!G12) -> 14069.068 | I9: ='Balance Sheet'!I12-IF(I$3=DATE(2026,1,1),1300000,'Balance Sheet'!H12) -> 24482.184 | J9: ='Balance Sheet'!J12-IF(J$3=DATE(2026,1,1),1300000,'Balance Sheet'!I12) -> 19322.381 | ... N9: ='Balance Sheet'!N12-IF(N$3=DATE(2026,1,1),1300000,'Balance Sheet'!M12) -> 40853.4
B10: Cash Flow from Operations | C10: =SUM(C4:C9) -> -1415842.7 | D10: =SUM(D4:D9) -> -995832.52 | E10: =SUM(E4:E9) -> -976105.89 | F10: =SUM(F4:F9) -> -962835.51 | G10: =SUM(G4:G9) -> -917538.1 | H10: =SUM(H4:H9) -> -921355.16 | I10: =SUM(I4:I9) -> -939165.95 | J10: =SUM(J4:J9) -> -726519.35 | ... N10: =SUM(N4:N9) -> -421564.05
B12: Capital Expenditures | C12: =-'Income Statement'!C4*Capex_Pct -> -101472.21 | D12: =-'Income Statement'!D4*Capex_Pct -> -102664.57 | E12: =-'Income Statement'!E4*Capex_Pct -> -104321.83 | F12: =-'Income Statement'!F4*Capex_Pct -> -105879.48 | G12: =-'Income Statement'!G4*Capex_Pct -> -106666.01 | H12: =-'Income Statement'!H4*Capex_Pct -> -107670.94 | I12: =-'Income Statement'!I4*Capex_Pct -> -109419.67 | J12: =-'Income Statement'!J4*Capex_Pct -> -110799.84 | ... N12: =-'Income Statement'!N4*Capex_Pct -> -119252.72
B13: Cash Flow from Investing | C13: =C12 -> -101472.21 | D13: =D12 -> -102664.57 | E13: =E12 -> -104321.83 | F13: =F12 -> -105879.48 | G13: =G12 -> -106666.01 | H13: =H12 -> -107670.94 | I13: =I12 -> -109419.67 | J13: =J12 -> -110799.84 | ... N13: =N12 -> -119252.72
B15: Debt Issuance / (Repayment) | C15: =0 -> 0 | D15: =0 -> 0 | E15: =0 -> 0 | F15: =0 -> 0 | G15: =0 -> 0 | H15: =0 -> 0 | I15: =0 -> 0 | J15: =0 -> 0 | ... N15: =0 -> 0
B16: Net Change in Cash | C16: =SUM(C10,C13,C15) -> -1517314.9 | D16: =SUM(D10,D13,D15) -> -1098497.1 | E16: =SUM(E10,E13,E15) -> -1080427.7 | F16: =SUM(F10,F13,F15) -> -1068715 | G16: =SUM(G10,G13,G15) -> -1024204.1 | H16: =SUM(H10,H13,H15) -> -1029026.1 | I16: =SUM(I10,I13,I15) -> -1048585.6 | J16: =SUM(J10,J13,J15) -> -837319.19 | ... N16: =SUM(N10,N13,N15) -> -540816.77
B17: Ending Cash | C17: =Opening_Cash+C16 -> 16482685 | D17: =C17+D16 -> 15384188 | E17: =D17+E16 -> 14303760 | F17: =E17+F16 -> 13235045 | G17: =F17+G16 -> 12210841 | H17: =G17+H16 -> 11181815 | I17: =H17+I16 -> 10133230 | J17: =I17+J16 -> 9295910.3 | K17: =J17+K16 -> 8447691.2 | ... N17: =M17+N16 -> 6673852.6

Sheet SaaS Metrics Dashboard
A1: SaaS Metrics Dashboard | board-level operating health
C3: 46023 | D3: 46054 | E3: 46082 | F3: 46113 | G3: 46143 | H3: 46174 | I3: 46204 | J3: 46235 | K3: 46266 | L3: 46296 | M3: 46327 | N3: 46357
B4: ARR | C4: ='Revenue Forecast'!C34 -> 49019718 | D4: ='Revenue Forecast'!D34 -> 49538266 | E4: ='Revenue Forecast'!E34 -> 50610694 | F4: ='Revenue Forecast'!F34 -> 51033607 | G4: ='Revenue Forecast'!G34 -> 51365761 | H4: ='Revenue Forecast'!H34 -> 51998343 | I4: ='Revenue Forecast'!I34 -> 53044539 | J4: ='Revenue Forecast'!J34 -> 53323307 | ... N4: ='Revenue Forecast'!N34 -> 58264251
B5: MRR | C5: =C4/12 -> 4084976.5 | D5: =D4/12 -> 4128188.9 | E5: =E4/12 -> 4217557.8 | F5: =F4/12 -> 4252800.6 | G5: =G4/12 -> 4280480.1 | H5: =H4/12 -> 4333195.3 | I5: =I4/12 -> 4420378.3 | J5: =J4/12 -> 4443608.9 | ... N5: =N4/12 -> 4855354.3
B6: NRR | C6: =IFERROR(('ARR Bridge'!C4+'ARR Bridge'!C6-'ARR Bridge'!C7-'ARR Bridge'!C8)/'ARR Bridge'!C4,0) -> 0.99139556 | D6: =IFERROR(('ARR Bridge'!D4+'ARR Bridge'!D6-'ARR Bridge'!D7-'ARR Bridge'!D8)/'ARR Bridge'!D4,0) -> 0.95602351 | E6: =IFERROR(('ARR Bridge'!E4+'ARR Bridge'!E6-'ARR Bridge'!E7-'ARR Bridge'!E8)/'ARR Bridge'!E4,0) -> 0.97871856 | F6: =IFERROR(('ARR Bridge'!F4+'ARR Bridge'!F6-'ARR Bridge'!F7-'ARR Bridge'!F8)/'ARR Bridge'!F4,0) -> 0.99831603 | G6: =IFERROR(('ARR Bridge'!G4+'ARR Bridge'!G6-'ARR Bridge'!G7-'ARR Bridge'!G8)/'ARR Bridge'!G4,0) -> 0.97864165 | H6: =IFERROR(('ARR Bridge'!H4+'ARR Bridge'!H6-'ARR Bridge'!H7-'ARR Bridge'!H8)/'ARR Bridge'!H4,0) -> 0.99854768 | I6: =IFERROR(('ARR Bridge'!I4+'ARR Bridge'!I6-'ARR Bridge'!I7-'ARR Bridge'!I8)/'ARR Bridge'!I4,0) -> 0.99294412 | J6: =IFERROR(('ARR Bridge'!J4+'ARR Bridge'!J6-'ARR Bridge'!J7-'ARR Bridge'!J8)/'ARR Bridge'!J4,0) -> 0.98046951 | ... N6: =IFERROR(('ARR Bridge'!N4+'ARR Bridge'!N6-'ARR Bridge'!N7-'ARR Bridge'!N8)/'ARR Bridge'!N4,0) -> 0.99712143
B7: GRR | C7: =IFERROR(('ARR Bridge'!C4-'ARR Bridge'!C7-'ARR Bridge'!C8)/'ARR Bridge'!C4,0) -> 0.98926304 | D7: =IFERROR(('ARR Bridge'!D4-'ARR Bridge'!D7-'ARR Bridge'!D8)/'ARR Bridge'!D4,0) -> 0.95565146 | E7: =IFERROR(('ARR Bridge'!E4-'ARR Bridge'!E7-'ARR Bridge'!E8)/'ARR Bridge'!E4,0) -> 0.97778339 | F7: =IFERROR(('ARR Bridge'!F4-'ARR Bridge'!F7-'ARR Bridge'!F8)/'ARR Bridge'!F4,0) -> 0.99469293 | G7: =IFERROR(('ARR Bridge'!G4-'ARR Bridge'!G7-'ARR Bridge'!G8)/'ARR Bridge'!G4,0) -> 0.97572234 | H7: =IFERROR(('ARR Bridge'!H4-'ARR Bridge'!H7-'ARR Bridge'!H8)/'ARR Bridge'!H4,0) -> 0.99454127 | I7: =IFERROR(('ARR Bridge'!I4-'ARR Bridge'!I7-'ARR Bridge'!I8)/'ARR Bridge'!I4,0) -> 0.99211113 | J7: =IFERROR(('ARR Bridge'!J4-'ARR Bridge'!J7-'ARR Bridge'!J8)/'ARR Bridge'!J4,0) -> 0.97939801 | ... N7: =IFERROR(('ARR Bridge'!N4-'ARR Bridge'!N7-'ARR Bridge'!N8)/'ARR Bridge'!N4,0) -> 0.99612322
B8: CAC | C8: =CAC_Per_Logo -> 42000 | D8: =CAC_Per_Logo -> 42000 | E8: =CAC_Per_Logo -> 42000 | F8: =CAC_Per_Logo -> 42000 | G8: =CAC_Per_Logo -> 42000 | H8: =CAC_Per_Logo -> 42000 | I8: =CAC_Per_Logo -> 42000 | J8: =CAC_Per_Logo -> 42000 | ... N8: =CAC_Per_Logo -> 42000
B9: LTV | C9: =IFERROR(((C5/COUNTIFS('Customer ARR Ledger'!$A$4:$A$10226,C$3,'Customer ARR Ledger'!$F$4:$F$10226,">0"))*Gross_Margin)/(Churn_Rate),0) -> 1006552.2 | D9: =IFERROR(((D5/COUNTIFS('Customer ARR Ledger'!$A$4:$A$10226,D$3,'Customer ARR Ledger'!$F$4:$F$10226,">0"))*Gross_Margin)/(Churn_Rate),0) -> 1010395.9 | E9: =IFERROR(((E5/COUNTIFS('Customer ARR Ledger'!$A$4:$A$10226,E$3,'Customer ARR Ledger'!$F$4:$F$10226,">0"))*Gross_Margin)/(Churn_Rate),0) -> 1039220.7 | F9: =IFERROR(((F5/COUNTIFS('Customer ARR Ledger'!$A$4:$A$10226,F$3,'Customer ARR Ledger'!$F$4:$F$10226,">0"))*Gross_Margin)/(Churn_Rate),0) -> 1027154.1 | G9: =IFERROR(((G5/COUNTIFS('Customer ARR Ledger'!$A$4:$A$10226,G$3,'Customer ARR Ledger'!$F$4:$F$10226,">0"))*Gross_Margin)/(Churn_Rate),0) -> 1023703.6 | H9: =IFERROR(((H5/COUNTIFS('Customer ARR Ledger'!$A$4:$A$10226,H$3,'Customer ARR Ledger'!$F$4:$F$10226,">0"))*Gross_Margin)/(Churn_Rate),0) -> 1013134.5 | I9: =IFERROR(((I5/COUNTIFS('Customer ARR Ledger'!$A$4:$A$10226,I$3,'Customer ARR Ledger'!$F$4:$F$10226,">0"))*Gross_Margin)/(Churn_Rate),0) -> 1010910.4 | J9: =IFERROR(((J5/COUNTIFS('Customer ARR Ledger'!$A$4:$A$10226,J$3,'Customer ARR Ledger'!$F$4:$F$10226,">0"))*Gross_Margin)/(Churn_Rate),0) -> 1009911.1 | ... N9: =IFERROR(((N5/COUNTIFS('Customer ARR Ledger'!$A$4:$A$10226,N$3,'Customer ARR Ledger'!$F$4:$F$10226,">0"))*Gross_Margin)/(Churn_Rate),0) -> 1042004.9
B10: LTV:CAC | C10: =IFERROR(C9/C8,0) -> 23.965529 | D10: =IFERROR(D9/D8,0) -> 24.057045 | E10: =IFERROR(E9/E8,0) -> 24.74335 | F10: =IFERROR(F9/F8,0) -> 24.456049 | G10: =IFERROR(G9/G8,0) -> 24.373896 | H10: =IFERROR(H9/H8,0) -> 24.122251 | I10: =IFERROR(I9/I8,0) -> 24.069294 | J10: =IFERROR(J9/J8,0) -> 24.045503 | ... N10: =IFERROR(N9/N8,0) -> 24.809639
B11: Rule of 40 | C11: =(C4/40003200)^(12/MONTH(C$3))-1+'Income Statement'!C15 -> 10.200267 | D11: =(D4/40003200)^(12/MONTH(D$3))-1+'Income Statement'!D15 -> 2.3546212 | E11: =(E4/40003200)^(12/MONTH(E$3))-1+'Income Statement'!E15 -> 1.3259801 | F11: =(F4/40003200)^(12/MONTH(F$3))-1+'Income Statement'!F15 -> 0.84735912 | G11: =(G4/40003200)^(12/MONTH(G$3))-1+'Income Statement'!G15 -> 0.59777411 | H11: =(H4/40003200)^(12/MONTH(H$3))-1+'Income Statement'!H15 -> 0.47039407 | I11: =(I4/40003200)^(12/MONTH(I$3))-1+'Income Statement'!I15 -> 0.41230566 | J11: =(J4/40003200)^(12/MONTH(J$3))-1+'Income Statement'!J15 -> 0.37503589 | ... N11: =(N4/40003200)^(12/MONTH(N$3))-1+'Income Statement'!N15 -> 0.38831262
B12: Magic Number | C12: =IFERROR(('Revenue Forecast'!C33-IF(C$3=DATE(2026,1,1),3300000,'Revenue Forecast'!B33))*4/-'Income Statement'!C9,0) -> 1.5407828 | D12: =IFERROR(('Revenue Forecast'!D33-IF(D$3=DATE(2026,1,1),3300000,'Revenue Forecast'!C33))*4/-'Income Statement'!D9,0) -> 0.096709009 | E12: =IFERROR(('Revenue Forecast'!E33-IF(E$3=DATE(2026,1,1),3300000,'Revenue Forecast'!D33))*4/-'Income Statement'!E9,0) -> 0.1342413 | F12: =IFERROR(('Revenue Forecast'!F33-IF(F$3=DATE(2026,1,1),3300000,'Revenue Forecast'!E33))*4/-'Income Statement'!F9,0) -> 0.12503282 | G12: =IFERROR(('Revenue Forecast'!G33-IF(G$3=DATE(2026,1,1),3300000,'Revenue Forecast'!F33))*4/-'Income Statement'!G9,0) -> 0.062777819 | H12: =IFERROR(('Revenue Forecast'!H33-IF(H$3=DATE(2026,1,1),3300000,'Revenue Forecast'!G33))*4/-'Income Statement'!H9,0) -> 0.080106411 | I12: =IFERROR(('Revenue Forecast'!I33-IF(I$3=DATE(2026,1,1),3300000,'Revenue Forecast'!H33))*4/-'Income Statement'!I9,0) -> 0.1381562 | J12: =IFERROR(('Revenue Forecast'!J33-IF(J$3=DATE(2026,1,1),3300000,'Revenue Forecast'!I33))*4/-'Income Statement'!J9,0) -> 0.11263359 | ... N12: =IFERROR(('Revenue Forecast'!N33-IF(N$3=DATE(2026,1,1),3300000,'Revenue Forecast'!M33))*4/-'Income Statement'!N9,0) -> 0.24523566
B13: Burn Multiple | C13: =IFERROR(MAX(0,-'Cash Flow Statement'!C16)/('Revenue Forecast'!C34-IF(C$3=DATE(2026,1,1),40003200,'Revenue Forecast'!B34)),0) -> 0.1682817 | D13: =IFERROR(MAX(0,-'Cash Flow Statement'!D16)/('Revenue Forecast'!D34-IF(D$3=DATE(2026,1,1),40003200,'Revenue Forecast'!C34)),0) -> 2.1184062 | E13: =IFERROR(MAX(0,-'Cash Flow Statement'!E16)/('Revenue Forecast'!E34-IF(E$3=DATE(2026,1,1),40003200,'Revenue Forecast'!D34)),0) -> 1.0074601 | F13: =IFERROR(MAX(0,-'Cash Flow Statement'!F16)/('Revenue Forecast'!F34-IF(F$3=DATE(2026,1,1),40003200,'Revenue Forecast'!E34)),0) -> 2.5270298 | G13: =IFERROR(MAX(0,-'Cash Flow Statement'!G16)/('Revenue Forecast'!G34-IF(G$3=DATE(2026,1,1),40003200,'Revenue Forecast'!F34)),0) -> 3.083526 | H13: =IFERROR(MAX(0,-'Cash Flow Statement'!H16)/('Revenue Forecast'!H34-IF(H$3=DATE(2026,1,1),40003200,'Revenue Forecast'!G34)),0) -> 1.6267064 | I13: =IFERROR(MAX(0,-'Cash Flow Statement'!I16)/('Revenue Forecast'!I34-IF(I$3=DATE(2026,1,1),40003200,'Revenue Forecast'!H34)),0) -> 1.0022843 | J13: =IFERROR(MAX(0,-'Cash Flow Statement'!J16)/('Revenue Forecast'!J34-IF(J$3=DATE(2026,1,1),40003200,'Revenue Forecast'!I34)),0) -> 3.0036471 | ... N13: =IFERROR(MAX(0,-'Cash Flow Statement'!N16)/('Revenue Forecast'!N34-IF(N$3=DATE(2026,1,1),40003200,'Revenue Forecast'!M34)),0) -> 0.26434295
B14: Cash Runway (months) | C14: =IF('Cash Flow Statement'!C16>=0,99,'Balance Sheet'!C5/-'Cash Flow Statement'!C16) -> 10.863062 | D14: =IF('Cash Flow Statement'!D16>=0,99,'Balance Sheet'!D5/-'Cash Flow Statement'!D16) -> 14.00476 | E14: =IF('Cash Flow Statement'!E16>=0,99,'Balance Sheet'!E5/-'Cash Flow Statement'!E16) -> 13.238979 | F14: =IF('Cash Flow Statement'!F16>=0,99,'Balance Sheet'!F5/-'Cash Flow Statement'!F16) -> 12.384074 | G14: =IF('Cash Flow Statement'!G16>=0,99,'Balance Sheet'!G5/-'Cash Flow Statement'!G16) -> 11.922273 | H14: =IF('Cash Flow Statement'!H16>=0,99,'Balance Sheet'!H5/-'Cash Flow Statement'!H16) -> 10.866406 | I14: =IF('Cash Flow Statement'!I16>=0,99,'Balance Sheet'!I5/-'Cash Flow Statement'!I16) -> 9.6637121 | J14: =IF('Cash Flow Statement'!J16>=0,99,'Balance Sheet'!J5/-'Cash Flow Statement'!J16) -> 11.101991 | ... N14: =IF('Cash Flow Statement'!N16>=0,99,'Balance Sheet'!N5/-'Cash Flow Statement'!N16) -> 12.340321
B15: EBITDA Margin | C15: ='Income Statement'!C15 -> -0.26311735 | D15: ='Income Statement'!D15 -> -0.25179982 | E15: ='Income Statement'!E15 -> -0.23608535 | F15: ='Income Statement'!F15 -> -0.22891456 | G15: ='Income Statement'!G15 -> -0.22439877 | H15: ='Income Statement'!H15 -> -0.2192279 | I15: ='Income Statement'!I15 -> -0.2097986 | J15: ='Income Statement'!J15 -> -0.163946 | ... N15: ='Income Statement'!N15 -> -0.068177143

Sheet Budget vs Actual
A1: Budget vs Actual | volume / price-mix decomposition and materiality flags
C3: 46023 | D3: 46054 | E3: 46082 | F3: 46113 | G3: 46143 | H3: 46174 | I3: 46204 | J3: 46235 | K3: 46266 | L3: 46296 | M3: 46327 | N3: 46357
B4: Revenue Budget | C4: =SUMIFS($R$25:$R$84,$P$25:$P$84,C$3) -> 3390800 | D4: =SUMIFS($R$25:$R$84,$P$25:$P$84,D$3) -> 3441662 | E4: =SUMIFS($R$25:$R$84,$P$25:$P$84,E$3) -> 3778453 | F4: =SUMIFS($R$25:$R$84,$P$25:$P$84,F$3) -> 3545686 | G4: =SUMIFS($R$25:$R$84,$P$25:$P$84,G$3) -> 3598872 | H4: =SUMIFS($R$25:$R$84,$P$25:$P$84,H$3) -> 3951047 | I4: =SUMIFS($R$25:$R$84,$P$25:$P$84,I$3) -> 3707647 | J4: =SUMIFS($R$25:$R$84,$P$25:$P$84,J$3) -> 3763262 | ... N4: =SUMIFS($R$25:$R$84,$P$25:$P$84,N$3) -> 4320246
B5: Volume Variance | C5: =(SUMIFS($W$25:$W$84,$P$25:$P$84,C$3)-SUMIFS($V$25:$V$84,$P$25:$P$84,C$3))*SUMIFS($X$25:$X$84,$P$25:$P$84,C$3) -> -75351.11 | D5: =(SUMIFS($W$25:$W$84,$P$25:$P$84,D$3)-SUMIFS($V$25:$V$84,$P$25:$P$84,D$3))*SUMIFS($X$25:$X$84,$P$25:$P$84,D$3) -> -149637.48 | E5: =(SUMIFS($W$25:$W$84,$P$25:$P$84,E$3)-SUMIFS($V$25:$V$84,$P$25:$P$84,E$3))*SUMIFS($X$25:$X$84,$P$25:$P$84,E$3) -> 82140.29 | F5: =(SUMIFS($W$25:$W$84,$P$25:$P$84,F$3)-SUMIFS($V$25:$V$84,$P$25:$P$84,F$3))*SUMIFS($X$25:$X$84,$P$25:$P$84,F$3) -> 75440.13 | G5: =(SUMIFS($W$25:$W$84,$P$25:$P$84,G$3)-SUMIFS($V$25:$V$84,$P$25:$P$84,G$3))*SUMIFS($X$25:$X$84,$P$25:$P$84,G$3) -> 0 | H5: =(SUMIFS($W$25:$W$84,$P$25:$P$84,H$3)-SUMIFS($V$25:$V$84,$P$25:$P$84,H$3))*SUMIFS($X$25:$X$84,$P$25:$P$84,H$3) -> -161267.22 | I5: =(SUMIFS($W$25:$W$84,$P$25:$P$84,I$3)-SUMIFS($V$25:$V$84,$P$25:$P$84,I$3))*SUMIFS($X$25:$X$84,$P$25:$P$84,I$3) -> -222458.85 | J5: =(SUMIFS($W$25:$W$84,$P$25:$P$84,J$3)-SUMIFS($V$25:$V$84,$P$25:$P$84,J$3))*SUMIFS($X$25:$X$84,$P$25:$P$84,J$3) -> -150530.48 | ... N5: =(SUMIFS($W$25:$W$84,$P$25:$P$84,N$3)-SUMIFS($V$25:$V$84,$P$25:$P$84,N$3))*SUMIFS($X$25:$X$84,$P$25:$P$84,N$3) -> 160009.1
B6: Price / Mix Variance | C6: =SUMIFS($W$25:$W$84,$P$25:$P$84,C$3)*(SUMIFS($Y$25:$Y$84,$P$25:$P$84,C$3)-SUMIFS($X$25:$X$84,$P$25:$P$84,C$3)) -> 24489.08 | D6: =SUMIFS($W$25:$W$84,$P$25:$P$84,D$3)*(SUMIFS($Y$25:$Y$84,$P$25:$P$84,D$3)-SUMIFS($X$25:$X$84,$P$25:$P$84,D$3)) -> 53270.8 | E6: =SUMIFS($W$25:$W$84,$P$25:$P$84,E$3)*(SUMIFS($Y$25:$Y$84,$P$25:$P$84,E$3)-SUMIFS($X$25:$X$84,$P$25:$P$84,E$3)) -> -14128.2 | F6: =SUMIFS($W$25:$W$84,$P$25:$P$84,F$3)*(SUMIFS($Y$25:$Y$84,$P$25:$P$84,F$3)-SUMIFS($X$25:$X$84,$P$25:$P$84,F$3)) -> 13201.92 | G6: =SUMIFS($W$25:$W$84,$P$25:$P$84,G$3)*(SUMIFS($Y$25:$Y$84,$P$25:$P$84,G$3)-SUMIFS($X$25:$X$84,$P$25:$P$84,G$3)) -> 43186.56 | H6: =SUMIFS($W$25:$W$84,$P$25:$P$84,H$3)*(SUMIFS($Y$25:$Y$84,$P$25:$P$84,H$3)-SUMIFS($X$25:$X$84,$P$25:$P$84,H$3)) -> 15078.54 | I6: =SUMIFS($W$25:$W$84,$P$25:$P$84,I$3)*(SUMIFS($Y$25:$Y$84,$P$25:$P$84,I$3)-SUMIFS($X$25:$X$84,$P$25:$P$84,I$3)) -> 22246.04 | J6: =SUMIFS($W$25:$W$84,$P$25:$P$84,J$3)*(SUMIFS($Y$25:$Y$84,$P$25:$P$84,J$3)-SUMIFS($X$25:$X$84,$P$25:$P$84,J$3)) -> -7526.4 | ... N6: =SUMIFS($W$25:$W$84,$P$25:$P$84,N$3)*(SUMIFS($Y$25:$Y$84,$P$25:$P$84,N$3)-SUMIFS($X$25:$X$84,$P$25:$P$84,N$3)) -> -8800.96
B7: Revenue Actual | C7: =SUMIFS($S$25:$S$84,$P$25:$P$84,C$3) -> 3339938 | D7: =SUMIFS($S$25:$S$84,$P$25:$P$84,D$3) -> 3345295 | E7: =SUMIFS($S$25:$S$84,$P$25:$P$84,E$3) -> 3846465 | F7: =SUMIFS($S$25:$S$84,$P$25:$P$84,F$3) -> 3634328 | G7: =SUMIFS($S$25:$S$84,$P$25:$P$84,G$3) -> 3642058 | H7: =SUMIFS($S$25:$S$84,$P$25:$P$84,H$3) -> 3804858 | I7: =SUMIFS($S$25:$S$84,$P$25:$P$84,I$3) -> 3507434 | J7: =SUMIFS($S$25:$S$84,$P$25:$P$84,J$3) -> 3605205 | ... N7: =SUMIFS($S$25:$S$84,$P$25:$P$84,N$3) -> 4471454
B8: Revenue Variance $ | C8: =SUM(C5:C6) -> -50862.03 | D8: =SUM(D5:D6) -> -96366.68 | E8: =SUM(E5:E6) -> 68012.09 | F8: =SUM(F5:F6) -> 88642.05 | G8: =SUM(G5:G6) -> 43186.56 | H8: =SUM(H5:H6) -> -146188.68 | I8: =SUM(I5:I6) -> -200212.81 | J8: =SUM(J5:J6) -> -158056.88 | ... N8: =SUM(N5:N6) -> 151208.14
B9: Revenue Variance % | C9: =IFERROR(C8/C4,0) -> -0.015000009 | D9: =IFERROR(D8/D4,0) -> -0.028000042 | E9: =IFERROR(E8/E4,0) -> 0.017999983 | F9: =IFERROR(F8/F4,0) -> 0.024999972 | G9: =IFERROR(G8/G4,0) -> 0.012000027 | H9: =IFERROR(H8/H4,0) -> -0.036999985 | I9: =IFERROR(I8/I4,0) -> -0.053999965 | J9: =IFERROR(J8/J4,0) -> -0.041999967 | ... N9: =IFERROR(N8/N4,0) -> 0.034999891
B11: Opex Budget | C11: =SUMIFS($T$25:$T$84,$P$25:$P$84,C$3) -> 3470000 | D11: =SUMIFS($T$25:$T$84,$P$25:$P$84,D$3) -> 3497760 | E11: =SUMIFS($T$25:$T$84,$P$25:$P$84,E$3) -> 3525742 | F11: =SUMIFS($T$25:$T$84,$P$25:$P$84,F$3) -> 3553947 | G11: =SUMIFS($T$25:$T$84,$P$25:$P$84,G$3) -> 3582380 | H11: =SUMIFS($T$25:$T$84,$P$25:$P$84,H$3) -> 3611039 | I11: =SUMIFS($T$25:$T$84,$P$25:$P$84,I$3) -> 3639928 | J11: =SUMIFS($T$25:$T$84,$P$25:$P$84,J$3) -> 3669046 | ... N11: =SUMIFS($T$25:$T$84,$P$25:$P$84,N$3) -> 3787872
B12: Sales Variance | C12: =SUMIFS($T$25:$T$84,$P$25:$P$84,C$3,$Q$25:$Q$84,"Sales")-SUMIFS($U$25:$U$84,$P$25:$P$84,C$3,$Q$25:$Q$84,"Sales") -> -42211 | D12: =SUMIFS($T$25:$T$84,$P$25:$P$84,D$3,$Q$25:$Q$84,"Sales")-SUMIFS($U$25:$U$84,$P$25:$P$84,D$3,$Q$25:$Q$84,"Sales") -> -37587 | E12: =SUMIFS($T$25:$T$84,$P$25:$P$84,E$3,$Q$25:$Q$84,"Sales")-SUMIFS($U$25:$U$84,$P$25:$P$84,E$3,$Q$25:$Q$84,"Sales") -> -35584 | F12: =SUMIFS($T$25:$T$84,$P$25:$P$84,F$3,$Q$25:$Q$84,"Sales")-SUMIFS($U$25:$U$84,$P$25:$P$84,F$3,$Q$25:$Q$84,"Sales") -> -35848 | G12: =SUMIFS($T$25:$T$84,$P$25:$P$84,G$3,$Q$25:$Q$84,"Sales")-SUMIFS($U$25:$U$84,$P$25:$P$84,G$3,$Q$25:$Q$84,"Sales") -> -41212 | H12: =SUMIFS($T$25:$T$84,$P$25:$P$84,H$3,$Q$25:$Q$84,"Sales")-SUMIFS($U$25:$U$84,$P$25:$P$84,H$3,$Q$25:$Q$84,"Sales") -> -39032 | I12: =SUMIFS($T$25:$T$84,$P$25:$P$84,I$3,$Q$25:$Q$84,"Sales")-SUMIFS($U$25:$U$84,$P$25:$P$84,I$3,$Q$25:$Q$84,"Sales") -> -22494 | J12: =SUMIFS($T$25:$T$84,$P$25:$P$84,J$3,$Q$25:$Q$84,"Sales")-SUMIFS($U$25:$U$84,$P$25:$P$84,J$3,$Q$25:$Q$84,"Sales") -> -43321 | ... N12: =SUMIFS($T$25:$T$84,$P$25:$P$84,N$3,$Q$25:$Q$84,"Sales")-SUMIFS($U$25:$U$84,$P$25:$P$84,N$3,$Q$25:$Q$84,"Sales") -> -36645
B13: Customer Success Variance | C13: =SUMIFS($T$25:$T$84,$P$25:$P$84,C$3,$Q$25:$Q$84,"Customer Success")-SUMIFS($U$25:$U$84,$P$25:$P$84,C$3,$Q$25:$Q$84,"Customer Success") -> 9147 | D13: =SUMIFS($T$25:$T$84,$P$25:$P$84,D$3,$Q$25:$Q$84,"Customer Success")-SUMIFS($U$25:$U$84,$P$25:$P$84,D$3,$Q$25:$Q$84,"Customer Success") -> 12419 | E13: =SUMIFS($T$25:$T$84,$P$25:$P$84,E$3,$Q$25:$Q$84,"Customer Success")-SUMIFS($U$25:$U$84,$P$25:$P$84,E$3,$Q$25:$Q$84,"Customer Success") -> 7582 | F13: =SUMIFS($T$25:$T$84,$P$25:$P$84,F$3,$Q$25:$Q$84,"Customer Success")-SUMIFS($U$25:$U$84,$P$25:$P$84,F$3,$Q$25:$Q$84,"Customer Success") -> 14600 | G13: =SUMIFS($T$25:$T$84,$P$25:$P$84,G$3,$Q$25:$Q$84,"Customer Success")-SUMIFS($U$25:$U$84,$P$25:$P$84,G$3,$Q$25:$Q$84,"Customer Success") -> 11204 | H13: =SUMIFS($T$25:$T$84,$P$25:$P$84,H$3,$Q$25:$Q$84,"Customer Success")-SUMIFS($U$25:$U$84,$P$25:$P$84,H$3,$Q$25:$Q$84,"Customer Success") -> 9127 | I13: =SUMIFS($T$25:$T$84,$P$25:$P$84,I$3,$Q$25:$Q$84,"Customer Success")-SUMIFS($U$25:$U$84,$P$25:$P$84,I$3,$Q$25:$Q$84,"Customer Success") -> 12085 | J13: =SUMIFS($T$25:$T$84,$P$25:$P$84,J$3,$Q$25:$Q$84,"Customer Success")-SUMIFS($U$25:$U$84,$P$25:$P$84,J$3,$Q$25:$Q$84,"Customer Success") -> 13773 | ... N13: =SUMIFS($T$25:$T$84,$P$25:$P$84,N$3,$Q$25:$Q$84,"Customer Success")-SUMIFS($U$25:$U$84,$P$25:$P$84,N$3,$Q$25:$Q$84,"Customer Success") -> 11213
B14: Marketing Variance | C14: =SUMIFS($T$25:$T$84,$P$25:$P$84,C$3,$Q$25:$Q$84,"Marketing")-SUMIFS($U$25:$U$84,$P$25:$P$84,C$3,$Q$25:$Q$84,"Marketing") -> -39247 | D14: =SUMIFS($T$25:$T$84,$P$25:$P$84,D$3,$Q$25:$Q$84,"Marketing")-SUMIFS($U$25:$U$84,$P$25:$P$84,D$3,$Q$25:$Q$84,"Marketing") -> -43603 | E14: =SUMIFS($T$25:$T$84,$P$25:$P$84,E$3,$Q$25:$Q$84,"Marketing")-SUMIFS($U$25:$U$84,$P$25:$P$84,E$3,$Q$25:$Q$84,"Marketing") -> -45209 | F14: =SUMIFS($T$25:$T$84,$P$25:$P$84,F$3,$Q$25:$Q$84,"Marketing")-SUMIFS($U$25:$U$84,$P$25:$P$84,F$3,$Q$25:$Q$84,"Marketing") -> -42547 | G14: =SUMIFS($T$25:$T$84,$P$25:$P$84,G$3,$Q$25:$Q$84,"Marketing")-SUMIFS($U$25:$U$84,$P$25:$P$84,G$3,$Q$25:$Q$84,"Marketing") -> -46777 | H14: =SUMIFS($T$25:$T$84,$P$25:$P$84,H$3,$Q$25:$Q$84,"Marketing")-SUMIFS($U$25:$U$84,$P$25:$P$84,H$3,$Q$25:$Q$84,"Marketing") -> -52935 | I14: =SUMIFS($T$25:$T$84,$P$25:$P$84,I$3,$Q$25:$Q$84,"Marketing")-SUMIFS($U$25:$U$84,$P$25:$P$84,I$3,$Q$25:$Q$84,"Marketing") -> -42923 | J14: =SUMIFS($T$25:$T$84,$P$25:$P$84,J$3,$Q$25:$Q$84,"Marketing")-SUMIFS($U$25:$U$84,$P$25:$P$84,J$3,$Q$25:$Q$84,"Marketing") -> -44786 | ... N14: =SUMIFS($T$25:$T$84,$P$25:$P$84,N$3,$Q$25:$Q$84,"Marketing")-SUMIFS($U$25:$U$84,$P$25:$P$84,N$3,$Q$25:$Q$84,"Marketing") -> -52784
B15: Product & Engineering Variance | C15: =SUMIFS($T$25:$T$84,$P$25:$P$84,C$3,$Q$25:$Q$84,"Product & Engineering")-SUMIFS($U$25:$U$84,$P$25:$P$84,C$3,$Q$25:$Q$84,"Product & Engineering") -> -17031 | D15: =SUMIFS($T$25:$T$84,$P$25:$P$84,D$3,$Q$25:$Q$84,"Product & Engineering")-SUMIFS($U$25:$U$84,$P$25:$P$84,D$3,$Q$25:$Q$84,"Product & Engineering") -> -9519 | E15: =SUMIFS($T$25:$T$84,$P$25:$P$84,E$3,$Q$25:$Q$84,"Product & Engineering")-SUMIFS($U$25:$U$84,$P$25:$P$84,E$3,$Q$25:$Q$84,"Product & Engineering") -> -20399 | F15: =SUMIFS($T$25:$T$84,$P$25:$P$84,F$3,$Q$25:$Q$84,"Product & Engineering")-SUMIFS($U$25:$U$84,$P$25:$P$84,F$3,$Q$25:$Q$84,"Product & Engineering") -> -19543 | G15: =SUMIFS($T$25:$T$84,$P$25:$P$84,G$3,$Q$25:$Q$84,"Product & Engineering")-SUMIFS($U$25:$U$84,$P$25:$P$84,G$3,$Q$25:$Q$84,"Product & Engineering") -> -30748 | H15: =SUMIFS($T$25:$T$84,$P$25:$P$84,H$3,$Q$25:$Q$84,"Product & Engineering")-SUMIFS($U$25:$U$84,$P$25:$P$84,H$3,$Q$25:$Q$84,"Product & Engineering") -> -33590 | I15: =SUMIFS($T$25:$T$84,$P$25:$P$84,I$3,$Q$25:$Q$84,"Product & Engineering")-SUMIFS($U$25:$U$84,$P$25:$P$84,I$3,$Q$25:$Q$84,"Product & Engineering") -> -27873 | J15: =SUMIFS($T$25:$T$84,$P$25:$P$84,J$3,$Q$25:$Q$84,"Product & Engineering")-SUMIFS($U$25:$U$84,$P$25:$P$84,J$3,$Q$25:$Q$84,"Product & Engineering") -> -35141 | ... N15: =SUMIFS($T$25:$T$84,$P$25:$P$84,N$3,$Q$25:$Q$84,"Product & Engineering")-SUMIFS($U$25:$U$84,$P$25:$P$84,N$3,$Q$25:$Q$84,"Product & Engineering") -> -27194
B16: G&A Variance | C16: =SUMIFS($T$25:$T$84,$P$25:$P$84,C$3,$Q$25:$Q$84,"G&A")-SUMIFS($U$25:$U$84,$P$25:$P$84,C$3,$Q$25:$Q$84,"G&A") -> 25836 | D16: =SUMIFS($T$25:$T$84,$P$25:$P$84,D$3,$Q$25:$Q$84,"G&A")-SUMIFS($U$25:$U$84,$P$25:$P$84,D$3,$Q$25:$Q$84,"G&A") -> 16618 | E16: =SUMIFS($T$25:$T$84,$P$25:$P$84,E$3,$Q$25:$Q$84,"G&A")-SUMIFS($U$25:$U$84,$P$25:$P$84,E$3,$Q$25:$Q$84,"G&A") -> 19556 | F16: =SUMIFS($T$25:$T$84,$P$25:$P$84,F$3,$Q$25:$Q$84,"G&A")-SUMIFS($U$25:$U$84,$P$25:$P$84,F$3,$Q$25:$Q$84,"G&A") -> 23065 | G16: =SUMIFS($T$25:$T$84,$P$25:$P$84,G$3,$Q$25:$Q$84,"G&A")-SUMIFS($U$25:$U$84,$P$25:$P$84,G$3,$Q$25:$Q$84,"G&A") -> 24747 | H16: =SUMIFS($T$25:$T$84,$P$25:$P$84,H$3,$Q$25:$Q$84,"G&A")-SUMIFS($U$25:$U$84,$P$25:$P$84,H$3,$Q$25:$Q$84,"G&A") -> 17528 | I16: =SUMIFS($T$25:$T$84,$P$25:$P$84,I$3,$Q$25:$Q$84,"G&A")-SUMIFS($U$25:$U$84,$P$25:$P$84,I$3,$Q$25:$Q$84,"G&A") -> 19017 | J16: =SUMIFS($T$25:$T$84,$P$25:$P$84,J$3,$Q$25:$Q$84,"G&A")-SUMIFS($U$25:$U$84,$P$25:$P$84,J$3,$Q$25:$Q$84,"G&A") -> 24144 | ... N16: =SUMIFS($T$25:$T$84,$P$25:$P$84,N$3,$Q$25:$Q$84,"G&A")-SUMIFS($U$25:$U$84,$P$25:$P$84,N$3,$Q$25:$Q$84,"G&A") -> 19460
B17: Opex Actual | C17: =SUMIFS($U$25:$U$84,$P$25:$P$84,C$3) -> 3533506 | D17: =SUMIFS($U$25:$U$84,$P$25:$P$84,D$3) -> 3559432 | E17: =SUMIFS($U$25:$U$84,$P$25:$P$84,E$3) -> 3599796 | F17: =SUMIFS($U$25:$U$84,$P$25:$P$84,F$3) -> 3614220 | G17: =SUMIFS($U$25:$U$84,$P$25:$P$84,G$3) -> 3665166 | H17: =SUMIFS($U$25:$U$84,$P$25:$P$84,H$3) -> 3709941 | I17: =SUMIFS($U$25:$U$84,$P$25:$P$84,I$3) -> 3702116 | J17: =SUMIFS($U$25:$U$84,$P$25:$P$84,J$3) -> 3754377 | ... N17: =SUMIFS($U$25:$U$84,$P$25:$P$84,N$3) -> 3873822
B18: Opex Variance $ | C18: =C11-C17 -> -63506 | D18: =D11-D17 -> -61672 | E18: =E11-E17 -> -74054 | F18: =F11-F17 -> -60273 | G18: =G11-G17 -> -82786 | H18: =H11-H17 -> -98902 | I18: =I11-I17 -> -62188 | J18: =J11-J17 -> -85331 | ... N18: =N11-N17 -> -85950
B19: Opex Variance % | C19: =IFERROR(C18/C11,0) -> -0.018301441 | D19: =IFERROR(D18/D11,0) -> -0.017631856 | E19: =IFERROR(E18/E11,0) -> -0.021003806 | F19: =IFERROR(F18/F11,0) -> -0.016959454 | G19: =IFERROR(G18/G11,0) -> -0.023109218 | H19: =IFERROR(H18/H11,0) -> -0.027388793 | I19: =IFERROR(I18/I11,0) -> -0.017084953 | J19: =IFERROR(J18/J11,0) -> -0.023256999 | ... N19: =IFERROR(N18/N11,0) -> -0.022690841
P24: month | Q24: department | R24: revenue_budget | S24: revenue_actual | T24: opex_budget | U24: opex_actual | V24: units_budget | W24: units_actual | X24: arpa_budget | Y24: arpa_actual
P25: 46023 | Q25: Sales | R25: 3390800 | S25: 3339938 | T25: 920000 | U25: 962211 | V25: 45 | W25: 44 | X25: 75351.11 | Y25: 75907.68
P26: 46023 | Q26: Customer Success | R26: 0 | S26: 0 | T26: 390000 | U26: 380853 | V26: 0 | W26: 0 | X26: 0 | Y26: 0
P27: 46023 | Q27: Marketing | R27: 0 | S27: 0 | T27: 520000 | U27: 559247 | V27: 0 | W27: 0 | X27: 0 | Y27: 0
P28: 46023 | Q28: Product & Engineering | R28: 0 | S28: 0 | T28: 1160000 | U28: 1177031 | V28: 0 | W28: 0 | X28: 0 | Y28: 0
P29: 46023 | Q29: G&A | R29: 0 | S29: 0 | T29: 480000 | U29: 454164 | V29: 0 | W29: 0 | X29: 0 | Y29: 0
P30: 46054 | Q30: Sales | R30: 3441662 | S30: 3345295 | T30: 927360 | U30: 964947 | V30: 46 | W30: 44 | X30: 74818.74 | Y30: 76029.44
P31: 46054 | Q31: Customer Success | R31: 0 | S31: 0 | T31: 393120 | U31: 380701 | V31: 0 | W31: 0 | X31: 0 | Y31: 0
P32: 46054 | Q32: Marketing | R32: 0 | S32: 0 | T32: 524160 | U32: 567763 | V32: 0 | W32: 0 | X32: 0 | Y32: 0
P33: 46054 | Q33: Product & Engineering | R33: 0 | S33: 0 | T33: 1169280 | U33: 1178799 | V33: 0 | W33: 0 | X33: 0 | Y33: 0
P34: 46054 | Q34: G&A | R34: 0 | S34: 0 | T34: 483840 | U34: 467222 | V34: 0 | W34: 0 | X34: 0 | Y34: 0
P35: 46082 | Q35: Sales | R35: 3778453 | S35: 3846465 | T35: 934779 | U35: 970363 | V35: 46 | W35: 47 | X35: 82140.29 | Y35: 81839.69
P36: 46082 | Q36: Customer Success | R36: 0 | S36: 0 | T36: 396265 | U36: 388683 | V36: 0 | W36: 0 | X36: 0 | Y36: 0
... P84: 46357 | Q84: G&A | R84: 0 | S84: 0 | T84: 523971 | U84: 504511 | V84: 0 | W84: 0 | X84: 0 | Y84: 0

Sheet Sensitivity Analysis
A1: Sensitivity Analysis | ending cash and runway under churn / hiring combinations
K2: =Churn_Rate -> 0.011
B3: Ending Cash Sensitivity ($M) | K3: =Hiring_Pace -> 1
K4: =('Balance Sheet'!N5+((Churn_Rate-K2)*'Revenue Forecast'!N34*0.65)-((K3-Hiring_Pace)*SUM('Headcount & Opex Plan'!N12:N16)*12))/1000000 -> 6.6738526
B5: Hiring / Churn | C5: ='Balance Sheet'!N5/1000000 -> 6.6738526 | D5: 0.006 | E5: 0.009 | F5: 0.012 | G5: 0.015 | H5: 0.018 | K5: =MAX(0,K4/MAX(0.1,-'Cash Flow Statement'!N16/1000000)) -> 12.340321
C6: 0.75 | D6: 6.6738526 | E6: 6.6738526 | F6: 6.6738526 | G6: 6.6738526 | H6: 6.6738526
C7: 0.875 | D7: 6.6738526 | E7: 6.6738526 | F7: 6.6738526 | G7: 6.6738526 | H7: 6.6738526
C8: 1 | D8: 6.6738526 | E8: 6.6738526 | F8: 6.6738526 | G8: 6.6738526 | H8: 6.6738526
C9: 1.125 | D9: 6.6738526 | E9: 6.6738526 | F9: 6.6738526 | G9: 6.6738526 | H9: 6.6738526
C10: 1.25 | D10: 6.6738526 | E10: 6.6738526 | F10: 6.6738526 | G10: 6.6738526 | H10: 6.6738526
B13: Runway Sensitivity (months)
B15: Hiring / Churn | C15: ='SaaS Metrics Dashboard'!N14 -> 12.340321 | D15: 0.006 | E15: 0.009 | F15: 0.012 | G15: 0.015 | H15: 0.018
C16: 0.75 | D16: 12.340321 | E16: 12.340321 | F16: 12.340321 | G16: 12.340321 | H16: 12.340321
C17: 0.875 | D17: 12.340321 | E17: 12.340321 | F17: 12.340321 | G17: 12.340321 | H17: 12.340321
C18: 1 | D18: 12.340321 | E18: 12.340321 | F18: 12.340321 | G18: 12.340321 | H18: 12.340321
C19: 1.125 | D19: 12.340321 | E19: 12.340321 | F19: 12.340321 | G19: 12.340321 | H19: 12.340321
C20: 1.25 | D20: 12.340321 | E20: 12.340321 | F20: 12.340321 | G20: 12.340321 | H20: 12.340321
B23: Tornado Chart Source | impact on ending cash ($M)
B24: Driver | C24: Low | D24: Base | E24: High
B25: Churn rate | C25: =H8 -> 6.6738526 | D25: =F8 -> 6.6738526 | E25: =D8 -> 6.6738526
B26: Hiring pace | C26: =F10 -> 6.6738526 | D26: =F8 -> 6.6738526 | E26: =F6 -> 6.6738526
B27: Pipeline conversion | C27: =D6 -> 6.6738526 | D27: =F8 -> 6.6738526 | E27: =H10 -> 6.6738526
B28: Gross margin | C28: =F8-1.2 -> 5.4738526 | D28: =F8 -> 6.6738526 | E28: =F8+1 -> 7.6738526

Sheet Cohort LTV Analysis
A1: Cohort LTV Analysis | acquisition-quarter economics
B3: Cohort Quarter | C3: New Logos | D3: Opening MRR | E3: Current MRR | F3: Retention % | G3: CAC Spend | H3: LTV | I3: LTV:CAC | J3: Payback (months)
B4: 45292 | C4: =COUNTIFS('Customer ARR Ledger'!$H$4:$H$10226,">="&B4,'Customer ARR Ledger'!$H$4:$H$10226,"<"&DATE(2024,4,1),'Customer ARR Ledger'!$G$4:$G$10226,"new") -> 247 | D4: =SUMIFS('Customer ARR Ledger'!$F$4:$F$10226,'Customer ARR Ledger'!$H$4:$H$10226,">="&B4,'Customer ARR Ledger'!$H$4:$H$10226,"<"&DATE(2024,4,1),'Customer ARR Ledger'!$G$4:$G$10226,"new") -> 3415000 | E4: =SUMIFS('Customer ARR Ledger'!$F$4:$F$10226,'Customer ARR Ledger'!$H$4:$H$10226,">="&B4,'Customer ARR Ledger'!$H$4:$H$10226,"<"&DATE(2024,4,1),'Customer ARR Ledger'!$A$4:$A$10226,DATE(2026,12,1)) -> 2488700 | F4: =IFERROR(E4/D4,0) -> 0.72875549 | G4: =C4*CAC_Per_Logo -> 10374000 | H4: =IFERROR((D4/C4)*Gross_Margin/Churn_Rate,0) -> 1011805.3 | I4: =IFERROR(H4/CAC_Per_Logo,0) -> 24.090602 | J4: =IFERROR(CAC_Per_Logo/((D4/C4)*Gross_Margin),0) -> 3.7736329
B5: 45383 | C5: =COUNTIFS('Customer ARR Ledger'!$H$4:$H$10226,">="&B5,'Customer ARR Ledger'!$H$4:$H$10226,"<"&DATE(2024,7,1),'Customer ARR Ledger'!$G$4:$G$10226,"new") -> 19 | D5: =SUMIFS('Customer ARR Ledger'!$F$4:$F$10226,'Customer ARR Ledger'!$H$4:$H$10226,">="&B5,'Customer ARR Ledger'!$H$4:$H$10226,"<"&DATE(2024,7,1),'Customer ARR Ledger'!$G$4:$G$10226,"new") -> 305100 | E5: =SUMIFS('Customer ARR Ledger'!$F$4:$F$10226,'Customer ARR Ledger'!$H$4:$H$10226,">="&B5,'Customer ARR Ledger'!$H$4:$H$10226,"<"&DATE(2024,7,1),'Customer ARR Ledger'!$A$4:$A$10226,DATE(2026,12,1)) -> 109900 | F5: =IFERROR(E5/D5,0) -> 0.36020977 | G5: =C5*CAC_Per_Logo -> 798000 | H5: =IFERROR((D5/C5)*Gross_Margin/Churn_Rate,0) -> 1175145.9 | I5: =IFERROR(H5/CAC_Per_Logo,0) -> 27.979665 | J5: =IFERROR(CAC_Per_Logo/((D5/C5)*Gross_Margin),0) -> 3.2491129
B6: 45474 | C6: =COUNTIFS('Customer ARR Ledger'!$H$4:$H$10226,">="&B6,'Customer ARR Ledger'!$H$4:$H$10226,"<"&DATE(2024,10,1),'Customer ARR Ledger'!$G$4:$G$10226,"new") -> 18 | D6: =SUMIFS('Customer ARR Ledger'!$F$4:$F$10226,'Customer ARR Ledger'!$H$4:$H$10226,">="&B6,'Customer ARR Ledger'!$H$4:$H$10226,"<"&DATE(2024,10,1),'Customer ARR Ledger'!$G$4:$G$10226,"new") -> 69500 | E6: =SUMIFS('Customer ARR Ledger'!$F$4:$F$10226,'Customer ARR Ledger'!$H$4:$H$10226,">="&B6,'Customer ARR Ledger'!$H$4:$H$10226,"<"&DATE(2024,10,1),'Customer ARR Ledger'!$A$4:$A$10226,DATE(2026,12,1)) -> 40900 | F6: =IFERROR(E6/D6,0) -> 0.58848921 | G6: =C6*CAC_Per_Logo -> 756000 | H6: =IFERROR((D6/C6)*Gross_Margin/Churn_Rate,0) -> 282563.13 | I6: =IFERROR(H6/CAC_Per_Logo,0) -> 6.7276936 | J6: =IFERROR(CAC_Per_Logo/((D6/C6)*Gross_Margin),0) -> 13.512668
B7: 45566 | C7: =COUNTIFS('Customer ARR Ledger'!$H$4:$H$10226,">="&B7,'Customer ARR Ledger'!$H$4:$H$10226,"<"&DATE(2025,1,1),'Customer ARR Ledger'!$G$4:$G$10226,"new") -> 17 | D7: =SUMIFS('Customer ARR Ledger'!$F$4:$F$10226,'Customer ARR Ledger'!$H$4:$H$10226,">="&B7,'Customer ARR Ledger'!$H$4:$H$10226,"<"&DATE(2025,1,1),'Customer ARR Ledger'!$G$4:$G$10226,"new") -> 92400 | E7: =SUMIFS('Customer ARR Ledger'!$F$4:$F$10226,'Customer ARR Ledger'!$H$4:$H$10226,">="&B7,'Customer ARR Ledger'!$H$4:$H$10226,"<"&DATE(2025,1,1),'Customer ARR Ledger'!$A$4:$A$10226,DATE(2026,12,1)) -> 59800 | F7: =IFERROR(E7/D7,0) -> 0.64718615 | G7: =C7*CAC_Per_Logo -> 714000 | H7: =IFERROR((D7/C7)*Gross_Margin/Churn_Rate,0) -> 397764.71 | I7: =IFERROR(H7/CAC_Per_Logo,0) -> 9.4705882 | J7: =IFERROR(CAC_Per_Logo/((D7/C7)*Gross_Margin),0) -> 9.5990966
B8: 45658 | C8: =COUNTIFS('Customer ARR Ledger'!$H$4:$H$10226,">="&B8,'Customer ARR Ledger'!$H$4:$H$10226,"<"&DATE(2025,4,1),'Customer ARR Ledger'!$G$4:$G$10226,"new") -> 17 | D8: =SUMIFS('Customer ARR Ledger'!$F$4:$F$10226,'Customer ARR Ledger'!$H$4:$H$10226,">="&B8,'Customer ARR Ledger'!$H$4:$H$10226,"<"&DATE(2025,4,1),'Customer ARR Ledger'!$G$4:$G$10226,"new") -> 170200 | E8: =SUMIFS('Customer ARR Ledger'!$F$4:$F$10226,'Customer ARR Ledger'!$H$4:$H$10226,">="&B8,'Customer ARR Ledger'!$H$4:$H$10226,"<"&DATE(2025,4,1),'Customer ARR Ledger'!$A$4:$A$10226,DATE(2026,12,1)) -> 142600 | F8: =IFERROR(E8/D8,0) -> 0.83783784 | G8: =C8*CAC_Per_Logo -> 714000 | H8: =IFERROR((D8/C8)*Gross_Margin/Churn_Rate,0) -> 732679.14 | I8: =IFERROR(H8/CAC_Per_Logo,0) -> 17.444742 | J8: =IFERROR(CAC_Per_Logo/((D8/C8)*Gross_Margin),0) -> 5.2112604
B9: 45748 | C9: =COUNTIFS('Customer ARR Ledger'!$H$4:$H$10226,">="&B9,'Customer ARR Ledger'!$H$4:$H$10226,"<"&DATE(2025,7,1),'Customer ARR Ledger'!$G$4:$G$10226,"new") -> 18 | D9: =SUMIFS('Customer ARR Ledger'!$F$4:$F$10226,'Customer ARR Ledger'!$H$4:$H$10226,">="&B9,'Customer ARR Ledger'!$H$4:$H$10226,"<"&DATE(2025,7,1),'Customer ARR Ledger'!$G$4:$G$10226,"new") -> 274000 | E9: =SUMIFS('Customer ARR Ledger'!$F$4:$F$10226,'Customer ARR Ledger'!$H$4:$H$10226,">="&B9,'Customer ARR Ledger'!$H$4:$H$10226,"<"&DATE(2025,7,1),'Customer ARR Ledger'!$A$4:$A$10226,DATE(2026,12,1)) -> 189000 | F9: =IFERROR(E9/D9,0) -> 0.68978102 | G9: =C9*CAC_Per_Logo -> 756000 | H9: =IFERROR((D9/C9)*Gross_Margin/Churn_Rate,0) -> 1113989.9 | I9: =IFERROR(H9/CAC_Per_Logo,0) -> 26.523569 | J9: =IFERROR(CAC_Per_Logo/((D9/C9)*Gross_Margin),0) -> 3.4274833
B10: 45839 | C10: =COUNTIFS('Customer ARR Ledger'!$H$4:$H$10226,">="&B10,'Customer ARR Ledger'!$H$4:$H$10226,"<"&DATE(2025,10,1),'Customer ARR Ledger'!$G$4:$G$10226,"new") -> 21 | D10: =SUMIFS('Customer ARR Ledger'!$F$4:$F$10226,'Customer ARR Ledger'!$H$4:$H$10226,">="&B10,'Customer ARR Ledger'!$H$4:$H$10226,"<"&DATE(2025,10,1),'Customer ARR Ledger'!$G$4:$G$10226,"new") -> 366400 | E10: =SUMIFS('Customer ARR Ledger'!$F$4:$F$10226,'Customer ARR Ledger'!$H$4:$H$10226,">="&B10,'Customer ARR Ledger'!$H$4:$H$10226,"<"&DATE(2025,10,1),'Customer ARR Ledger'!$A$4:$A$10226,DATE(2026,12,1)) -> 251400 | F10: =IFERROR(E10/D10,0) -> 0.68613537 | G10: =C10*CAC_Per_Logo -> 882000 | H10: =IFERROR((D10/C10)*Gross_Margin/Churn_Rate,0) -> 1276848.5 | I10: =IFERROR(H10/CAC_Per_Logo,0) -> 30.401154 | J10: =IFERROR(CAC_Per_Logo/((D10/C10)*Gross_Margin),0) -> 2.9903171
B11: 45931 | C11: =COUNTIFS('Customer ARR Ledger'!$H$4:$H$10226,">="&B11,'Customer ARR Ledger'!$H$4:$H$10226,"<"&DATE(2026,1,1),'Customer ARR Ledger'!$G$4:$G$10226,"new") -> 20 | D11: =SUMIFS('Customer ARR Ledger'!$F$4:$F$10226,'Customer ARR Ledger'!$H$4:$H$10226,">="&B11,'Customer ARR Ledger'!$H$4:$H$10226,"<"&DATE(2026,1,1),'Customer ARR Ledger'!$G$4:$G$10226,"new") -> 153100 | E11: =SUMIFS('Customer ARR Ledger'!$F$4:$F$10226,'Customer ARR Ledger'!$H$4:$H$10226,">="&B11,'Customer ARR Ledger'!$H$4:$H$10226,"<"&DATE(2026,1,1),'Customer ARR Ledger'!$A$4:$A$10226,DATE(2026,12,1)) -> 100400 | F11: =IFERROR(E11/D11,0) -> 0.65578054 | G11: =C11*CAC_Per_Logo -> 840000 | H11: =IFERROR((D11/C11)*Gross_Margin/Churn_Rate,0) -> 560206.82 | I11: =IFERROR(H11/CAC_Per_Logo,0) -> 13.338258 | J11: =IFERROR(CAC_Per_Logo/((D11/C11)*Gross_Margin),0) -> 6.8156647
B12: 46023 | C12: =COUNTIFS('Customer ARR Ledger'!$H$4:$H$10226,">="&B12,'Customer ARR Ledger'!$H$4:$H$10226,"<"&DATE(2026,4,1),'Customer ARR Ledger'!$G$4:$G$10226,"new") -> 21 | D12: =SUMIFS('Customer ARR Ledger'!$F$4:$F$10226,'Customer ARR Ledger'!$H$4:$H$10226,">="&B12,'Customer ARR Ledger'!$H$4:$H$10226,"<"&DATE(2026,4,1),'Customer ARR Ledger'!$G$4:$G$10226,"new") -> 182700 | E12: =SUMIFS('Customer ARR Ledger'!$F$4:$F$10226,'Customer ARR Ledger'!$H$4:$H$10226,">="&B12,'Customer ARR Ledger'!$H$4:$H$10226,"<"&DATE(2026,4,1),'Customer ARR Ledger'!$A$4:$A$10226,DATE(2026,12,1)) -> 181900 | F12: =IFERROR(E12/D12,0) -> 0.99562124 | G12: =C12*CAC_Per_Logo -> 882000 | H12: =IFERROR((D12/C12)*Gross_Margin/Churn_Rate,0) -> 636681.82 | I12: =IFERROR(H12/CAC_Per_Logo,0) -> 15.159091 | J12: =IFERROR(CAC_Per_Logo/((D12/C12)*Gross_Margin),0) -> 5.9970015
B13: 46113 | C13: =COUNTIFS('Customer ARR Ledger'!$H$4:$H$10226,">="&B13,'Customer ARR Ledger'!$H$4:$H$10226,"<"&DATE(2026,7,1),'Customer ARR Ledger'!$G$4:$G$10226,"new") -> 26 | D13: =SUMIFS('Customer ARR Ledger'!$F$4:$F$10226,'Customer ARR Ledger'!$H$4:$H$10226,">="&B13,'Customer ARR Ledger'!$H$4:$H$10226,"<"&DATE(2026,7,1),'Customer ARR Ledger'!$G$4:$G$10226,"new") -> 260400 | E13: =SUMIFS('Customer ARR Ledger'!$F$4:$F$10226,'Customer ARR Ledger'!$H$4:$H$10226,">="&B13,'Customer ARR Ledger'!$H$4:$H$10226,"<"&DATE(2026,7,1),'Customer ARR Ledger'!$A$4:$A$10226,DATE(2026,12,1)) -> 263400 | F13: =IFERROR(E13/D13,0) -> 1.0115207 | G13: =C13*CAC_Per_Logo -> 1092000 | H13: =IFERROR((D13/C13)*Gross_Margin/Churn_Rate,0) -> 732944.06 | I13: =IFERROR(H13/CAC_Per_Logo,0) -> 17.451049 | J13: =IFERROR(CAC_Per_Logo/((D13/C13)*Gross_Margin),0) -> 5.2093769
B14: 46204 | C14: =COUNTIFS('Customer ARR Ledger'!$H$4:$H$10226,">="&B14,'Customer ARR Ledger'!$H$4:$H$10226,"<"&DATE(2026,10,1),'Customer ARR Ledger'!$G$4:$G$10226,"new") -> 23 | D14: =SUMIFS('Customer ARR Ledger'!$F$4:$F$10226,'Customer ARR Ledger'!$H$4:$H$10226,">="&B14,'Customer ARR Ledger'!$H$4:$H$10226,"<"&DATE(2026,10,1),'Customer ARR Ledger'!$G$4:$G$10226,"new") -> 227900 | E14: =SUMIFS('Customer ARR Ledger'!$F$4:$F$10226,'Customer ARR Ledger'!$H$4:$H$10226,">="&B14,'Customer ARR Ledger'!$H$4:$H$10226,"<"&DATE(2026,10,1),'Customer ARR Ledger'!$A$4:$A$10226,DATE(2026,12,1)) -> 231400 | F14: =IFERROR(E14/D14,0) -> 1.0153576 | G14: =C14*CAC_Per_Logo -> 966000 | H14: =IFERROR((D14/C14)*Gross_Margin/Churn_Rate,0) -> 725136.36 | I14: =IFERROR(H14/CAC_Per_Logo,0) -> 17.265152 | J14: =IFERROR(CAC_Per_Logo/((D14/C14)*Gross_Margin),0) -> 5.2654673
B15: 46296 | C15: =COUNTIFS('Customer ARR Ledger'!$H$4:$H$10226,">="&B15,'Customer ARR Ledger'!$H$4:$H$10226,"<"&DATE(2027,1,1),'Customer ARR Ledger'!$G$4:$G$10226,"new") -> 24 | D15: =SUMIFS('Customer ARR Ledger'!$F$4:$F$10226,'Customer ARR Ledger'!$H$4:$H$10226,">="&B15,'Customer ARR Ledger'!$H$4:$H$10226,"<"&DATE(2027,1,1),'Customer ARR Ledger'!$G$4:$G$10226,"new") -> 278200 | E15: =SUMIFS('Customer ARR Ledger'!$F$4:$F$10226,'Customer ARR Ledger'!$H$4:$H$10226,">="&B15,'Customer ARR Ledger'!$H$4:$H$10226,"<"&DATE(2027,1,1),'Customer ARR Ledger'!$A$4:$A$10226,DATE(2026,12,1)) -> 278200 | F15: =IFERROR(E15/D15,0) -> 1 | G15: =C15*CAC_Per_Logo -> 1008000 | H15: =IFERROR((D15/C15)*Gross_Margin/Churn_Rate,0) -> 848299.24 | I15: =IFERROR(H15/CAC_Per_Logo,0) -> 20.197601 | J15: =IFERROR(CAC_Per_Logo/((D15/C15)*Gross_Margin),0) -> 4.5009846
